Workbook

Sheet 贾总
A1: 成都国圣工业有限公司（五星花）送货单
A2: 购货单位： 贾总 联系人：贾总 2026年01月22日 订单编号：26-010062A
A3: 产 品 型 号 | D3: 产 品 名 称 | E3: 数量/件 | F3: 规格/KG | G3: 数量/KG | H3: 单价/元 | I3: 金额/元 | J3: 备 注 | L3: 贾总
A4: 46043 | D4: 808 | E4: 1 | F4: 120 | G4: =E4*F4 -> 120 | H4: 7.2 | I4: =G4*H4 -> 864 | L4: 邻居杨总
A5: 46043 | D5: 807A | E5: 1 | F5: 40 | G5: =E5*F5 -> 40 | H5: 6.1 | I5: =G5*H5 -> 244
A6: 46043 | D6: 白浆：自备 | E6: 1 | F6: 180 | G6: =E6*F6 -> 180
A7: 46043 | D7: 1#浆:35% | E7: 1 | F7: 200 | G7: =E7*F7 -> 200
A8: 46043 | D8: 3#浆：:17% | E8: 1 | F8: 230 | G8: =E8*F8 -> 230
A9: 46043 | D9: 108树脂：自备 | E9: 1 | F9: 230 | G9: =E9*F9 -> 230
A10: 46043 | D10: 亮白（普）加工费 | E10: 1 | F10: =SUM(F4:F9) -> 1000 | G10: =E10*F10 -> 1000 | H10: 1 | I10: =G10*H10 -> 1000
A16: 大 写 人 民 币 | D16: =I16 -> 2108 | I16: =SUM(I4:I15) -> 2108
A17: 销售协议 | B17: 1.甲方所供上列产品均属检验合格产品，乙方如有异议，应在收货七天内书面提出，逾期不提出视为质量合格。
B18: 2.乙方每次要认真核对产品的型号.名称.数量.规格.重量.单价.金额，经甲乙双方经手人（库管）签字后具有
C19: 法律效力，必须按期付清货款（月结三十天），如有争议和纠纷，由甲方所在地方人民法院受理起诉。
B20: 3.本送货单一式四联， 白色联为存根联， 粉红色为客户联， 蓝色联为结款联， 黄色联为会计联。
A21: 销售单位（甲方）：成都国圣工业有限公司 电话：028-85852618
A22: 销售负责人：李秋林 销售送货人： 销售制单人： 购货单位经手人： | M22: ①

Sheet 贾总出货
A1: 3月 | J1: 金额总计 | K1: =SUM(K11:K143) -> 49665.95 | L1: 李总材料金额 | M1: ='24材料明细'!AQ402 -> 36321.35 | N1: 加工费 | O1: =K15+K21+K31+K34+K43+K49+K55+K61+K68+K72+K76+K83+K90+K93+K102+K109+K117+K124+K131+K139+K143 -> 12001.1 | P1: 成品 | Q1: =K94+Q13 -> 310
J2: 加工吨位 | K2: =SUM(I15+I21+I31+I34+I43+I49+I55+I61+I68+I72+I76+I83+I90+I93+I102+I109+I117+I124+I131+I139+I143)/1000 -> 10.6233 | L2: 包装桶金额 | M2: =K16+K22+K28+K84+K95 -> 1033.5 | N2: 总金额 | O2: =M1+Q1+O1+M2 -> 49665.95
A3: 日期 | B3: 单号 | C3: 产品型号 | F3: 产品名称 | G3: 数量/件 | H3: 规格/KG | I3: 数量/KG | J3: 单价/元 | K3: 金额/元 | L3: 备注 | M3: 金额合计
A4: 45351 | B4: 待改材料未入账 | C4: 45351 | F4: 108树脂：自备（三木） | G4: 1 | H4: 60 | I4: =G4*H4 -> 60
A5: 45351 | B5: 待改材料未入账 | C5: 45351 | F5: 环己酮: | G5: 1 | H5: 60 | I5: =G5*H5 -> 60
A6: 45351 | B6: 待改材料未入账 | C6: 45351 | F6: 1/2":715浆：自备 | G6: 1 | H6: 10 | I6: =G6*H6 -> 10
A7: 45351 | B7: 待改材料未入账 | C7: 45351 | F7: 30"：730浆：自备 | G7: 1 | H7: 10 | I7: =G7*H7 -> 10
A8: 45351 | B8: 待改材料未入账 | C8: 45351 | F8: 仲丁酯 | G8: 1 | H8: 60 | I8: =G8*H8 -> 60
A9: 45351 | B9: 待改材料未入账 | C9: 45351 | F9: ABS光油加工费 | G9: 1 | H9: 200 | I9: =G9*H9 -> 200
A10: 45351 | B10: 待改材料未入账 | C10: 45351 | F10: 另加包装桶：20L | G10: 11 | H10: 1 | I10: =G10*H10 -> 11
A11: 45353 | B11: 7号 | C11: 45352 | F11: 108树脂：自备（三木） | G11: 1 | H11: 60 | I11: =G11*H11 -> 60
A12: 45353 | B12: 7号 | C12: 45352 | F12: 环己酮: | G12: 1 | H12: 42 | I12: =G12*H12 -> 42 | J12: 10.3 | K12: =I12*J12 -> 432.6
A13: 45353 | B13: 7号 | C13: 45352 | F13: 1/2":715浆：自备 | G13: 1 | H13: 34 | I13: =G13*H13 -> 34 | L13: ABS光油：11桶*17KG
A14: 45353 | B14: 7号 | C14: 45352 | F14: 30"：730浆：自备 | G14: 1 | H14: 64 | I14: =G14*H14 -> 64 | M14: 商标：ABS光油/重量：17±0.1KG
A15: 45353 | B15: 7号 | C15: 45352 | F15: ABS光油加工费 | G15: 1 | H15: 200 | I15: =G15*H15 -> 200 | J15: 1 | K15: =I15*J15 -> 200
A16: 45353 | B16: 7号 | C16: 45352 | F16: 另加包装桶：20L | G16: 11 | H16: 1 | I16: =G16*H16 -> 11 | J16: 13 | K16: =I16*J16 -> 143 | L16: =SUM(K11:K16) -> 775.6
A17: 45360 | B17: 24号 | C17: 45356 | F17: 甲缩醛 | G17: 1 | H17: 8 | I17: =G17*H17 -> 8 | J17: 3.4 | K17: =I17*J17 -> 27.2
A18: 45360 | B18: 24号 | C18: 45356 | F18: 粗甲酯 | G18: 1 | H18: 3 | I18: =G18*H18 -> 3 | J18: 3.6 | K18: =I18*J18 -> 10.8
A19: 45360 | B19: 24号 | C19: 45356 | F19: 仲丁酯 | G19: 1 | H19: 4 | I19: =G19*H19 -> 4 | J19: 6.3 | K19: =I19*J19 -> 25.2
A20: 45360 | B20: 24号 | C20: 45356 | F20: 环己酮 | G20: 1 | H20: 3 | I20: =G20*H20 -> 3 | J20: 10.3 | K20: =I20*J20 -> 30.9
A21: 45360 | B21: 24号 | C21: 45356 | F21: 稀料加工费 | G21: 1 | H21: 18 | I21: =G21*H21 -> 18 | J21: 0.7 | K21: =I21*J21 -> 12.6
A22: 45360 | B22: 24号 | C22: 45356 | F22: 另加包装桶：20L | G22: 1 | H22: 1 | I22: =G22*H22 -> 1 | J22: 13 | K22: =I22*J22 -> 13 | L22: =SUM(K17:K22) -> 119.7
A23: 45360 | B23: 25号 | C23: 45357 | F23: 自提：黑色浆自备 | G23: 1 | H23: 3 | I23: =G23*H23 -> 3
A24: 45360 | B24: 25号 | C24: 45357 | F24: 自提：红色浆自备 | G24: 1 | H24: 3 | I24: =G24*H24 -> 3
A25: 45360 | B25: 25号 | C25: 45358 | F25: 自提：715浆自备 | G25: 1 | H25: 3 | I25: =G25*H25 -> 3
A26: 45360 | B26: 25号 | C26: 45358 | F26: 自提：730浆自备 | G26: 1 | H26: 3 | I26: =G26*H26 -> 3
A27: 45360 | B27: 25号 | C27: 45358 | F27: 自提：7025银粉 | G27: 1 | H27: 2 | I27: =G27*H27 -> 2 | J27: 50 | K27: =I27*J27 -> 100
A28: 45360 | B28: 25号 | C28: 45358 | F28: 另加包装桶：4L | G28: 5 | H28: 1 | I28: =G28*H28 -> 5 | J28: 5.5 | K28: =I28*J28 -> 27.5 | L28: =SUM(K23:K28) -> 127.5
A29: 45360 | B29: 26号 | C29: 45357 | F29: 仲丁酯 | G29: 2 | H29: 60 | I29: =G29*H29 -> 120 | J29: 6.3 | K29: =I29*J29 -> 756
A30: 45360 | B30: 26号 | C30: 45357 | F30: 715粉：自备 | G30: 2 | H30: 25 | I30: =G30*H30 -> 50
A31: 45360 | B31: 26号 | C31: 45357 | F31: 715浆加工费 | G31: 2 | H31: 85 | I31: =G31*H31 -> 170 | J31: 0.8 | K31: =I31*J31 -> 136
A32: 45360 | B32: 26号 | C32: 45357 | F32: 仲丁酯 | G32: 2 | H32: 135 | I32: =G32*H32 -> 270 | J32: 6.3 | K32: =I32*J32 -> 1701
A33: 45360 | B33: 26号 | C33: 45357 | F33: 30秒：自备 | G33: 2 | H33: 25 | I33: =G33*H33 -> 50
A34: 45360 | B34: 26号 | C34: 45357 | F34: 730浆加工费 | G34: 2 | H34: 160 | I34: =G34*H34 -> 320 | J34: 0.8 | K34: =I34*J34 -> 256 | L34: =SUM(K29:K34) -> 2849
A35: 45360 | B35: 27号 | C35: 45358 | F35: 1206树脂：自备（15%） | G35: 1 | H35: 25.5 | I35: =G35*H35 -> 25.5
A36: 45360 | B36: 27号 | C36: 45358 | F36: 108树脂：自备夏总（3%） | G36: 1 | H36: 5 | I36: =G36*H36 -> 5
A37: 45360 | B37: 27号 | C37: 45358 | F37: C311浆：自备（15%） | G37: 1 | H37: 25.5 | I37: =G37*H37 -> 25.5
A38: 45360 | B38: 27号 | C38: 45358 | F38: 715浆：自备（7%） | G38: 1 | H38: 12 | I38: =G38*H38 -> 12
A39: 45360 | B39: 27号 | C39: 45358 | F39: 730浆：自备（26%） | G39: 1 | H39: 44 | I39: =G39*H39 -> 44
A40: 45360 | B40: 27号 | C40: 45358 | F40: 350哑粉：自备（0.8%） | G40: 1 | H40: 1.5 | I40: =G40*H40 -> 1.5
A41: 45360 | B41: 27号 | C41: 45358 | F41: 808（15%） | G41: 1 | H41: 25.5 | I41: =G41*H41 -> 25.5 | J41: 10.3 | K41: 262.65
A42: 45360 | B42: 27号 | C42: 45358 | F42: 807+（18.2%) | G42: 1 | H42: 31 | I42: =G42*H42 -> 31 | J42: 6.3 | K42: 195.3
A43: 45360 | B43: 27号 | C43: 45358 | F43: 电镀黑半光漆加工费 | G43: 1 | H43: 170 | I43: =G43*H43 -> 170 | J43: 1 | K43: 170 | L43: 627.95
A44: 45370 | B44: 52号 | C44: 45363 | F44: 108树脂：自备（三木） | G44: 1 | H44: 32 | I44: =G44*H44 -> 32
A45: 45370 | B45: 52号 | C45: 45363 | F45: 分散剂：自备 | G45: 1 | H45: 3 | I45: =G45*H45 -> 3
A46: 45370 | B46: 52号 | C46: 45363 | F46: 996钛白粉：借黄总 | G46: 1 | H46: 100 | I46: =G46*H46 -> 100 | J46: 16 | K46: =I46*J46 -> 1600
A47: 45370 | B47: 52号 | C47: 45363 | F47: 丁酯 | G47: 1 | H47: 20 | I47: =G47*H47 -> 20 | J47: 9 | K47: =I47*J47 -> 180
A48: 45370 | B48: 52号 | C48: 45363 | F48: 二甲苯 | G48: 1 | H48: 20 | I48: =G48*H48 -> 20 | J48: 8.1 | K48: =I48*J48 -> 162
A49: 45370 | B49: 52号 | C49: 45363 | F49: 白色浆加工费 | G49: 1 | H49: 175 | I49: =G49*H49 -> 175 | J49: 3 | K49: =I49*J49 -> 525 | L49: =SUM(K46:K49) -> 2467
A50: 45370 | B50: 53号 | C50: 45370 | F50: 108树脂：自备 | G50: 1 | H50: 100 | I50: =G50*H50 -> 100
A51: 45370 | B51: 53号 | C51: 45370 | F51: 白浆：自备 | G51: 1 | H51: 100 | I51: =G51*H51 -> 100
A52: 45370 | B52: 53号 | C52: 45370 | F52: 715浆：自备 | G52: 1 | H52: 35 | I52: =G52*H52 -> 35
A53: 45370 | B53: 53号 | C53: 45370 | F53: 730浆：自备 | G53: 1 | H53: 190 | I53: =G53*H53 -> 190
A54: 45370 | B54: 53号 | C54: 45370 | F54: 808 | G54: 1 | H54: 75 | I54: =G54*H54 -> 75 | J54: 10.3 | K54: 772.5
A55: 45370 | B55: 53号 | C55: 45370 | F55: 亮白（普）加工费 | G55: 1 | H55: 500 | I55: =G55*H55 -> 500 | J55: 1 | K55: 500 | L55: 1272.5
A56: 45371 | B56: 57号 | C56: 45370 | F56: 108树脂：自备 | G56: 1 | H56: 32 | I56: =G56*H56 -> 32
A57: 45371 | B57: 57号 | C57: 45370 | F57: 14分散剂：自备 | G57: 1 | H57: 3 | I57: =G57*H57 -> 3
A58: 45371 | B58: 57号 | C58: 45370 | F58: 996钛白粉： | G58: 1 | H58: 100 | I58: =G58*H58 -> 100 | J58: 16 | K58: =I58*J58 -> 1600
A59: 45371 | B59: 57号 | C59: 45370 | F59: 丁酯 | G59: 1 | H59: 20 | I59: =G59*H59 -> 20 | J59: 9 | K59: =I59*J59 -> 180
A60: 45371 | B60: 57号 | C60: 45370 | F60: 二甲苯 | G60: 1 | H60: 20 | I60: =G60*H60 -> 20 | J60: 8.1 | K60: =I60*J60 -> 162
A61: 45371 | B61: 57号 | C61: 45370 | F61: 白色浆加工费 | G61: 1 | H61: 175 | I61: =G61*H61 -> 175 | J61: 3 | K61: =I61*J61 -> 525 | L61: =SUM(K58:K61) -> 2467
A62: 45373 | B62: 63号 | C62: 45373 | F62: 108树脂：自备 | G62: 1 | H62: 32 | I62: =G62*H62 -> 32
A63: 45373 | B63: 63号 | C63: 45373 | F63: 14分散剂：自备 | G63: 1 | H63: 3 | I63: =G63*H63 -> 3
A64: 45373 | B64: 63号 | C64: 45373 | F64: 防尘浆：自备 | G64: 1 | H64: 1.8 | I64: =G64*H64 -> 1.8
A65: 45373 | B65: 63号 | C65: 45373 | F65: 中黄粉：：自备 | G65: 1 | H65: 100 | I65: =G65*H65 -> 100 | K65: =I65*J65 -> 0
A66: 45373 | B66: 63号 | C66: 45373 | F66: 丁酯 | G66: 1 | H66: 20 | I66: =G66*H66 -> 20 | J66: 9 | K66: =I66*J66 -> 180 | M66: 净重156kg
A67: 45373 | B67: 63号 | C67: 45373 | F67: 二甲苯 | G67: 1 | H67: 20 | I67: =G67*H67 -> 20 | J67: 8.1 | K67: =I67*J67 -> 162
A68: 45373 | B68: 63号 | C68: 45373 | F68: ABS中黄浆加工费 | G68: 1 | H68: =SUM(H62:H67) -> 176.8 | I68: =G68*H68 -> 176.8 | J68: 5 | K68: =I68*J68 -> 884 | L68: =SUM(K65:K68) -> 1226
A69: 45374 | B69: 64号 | C69: 45374 | F69: 715粉：自备 | G69: 1 | H69: 300 | I69: =G69*H69 -> 300 | J69: 26
A70: 45374 | B70: 64号 | C70: 45374 | F70: 二甲苯 | G70: 1 | H70: 180 | I70: =G70*H70 -> 180 | J70: 8.1 | K70: =I70*J70 -> 1458
A71: 45374 | B71: 64号 | C71: 45374 | F71: 仲丁酯 | G71: 1 | H71: 540 | I71: =G71*H71 -> 540 | J71: 6.5 | K71: =I71*J71 -> 3510
A72: 45374 | B72: 64号 | C72: 45374 | F72: 715浆加工费 | G72: 1 | H72: =SUM(H69:H71) -> 1020 | I72: =G72*H72 -> 1020 | J72: 0.8 | K72: =I72*J72 -> 816
A73: 45374 | B73: 64号 | C73: 45374 | F73: 730粉：自备 | G73: 1 | H73: 200 | I73: =G73*H73 -> 200
A74: 45374 | B74: 64号 | C74: 45374 | F74: 仲丁酯 | G74: 1 | H74: 900 | I74: =G74*H74 -> 900 | J74: 6.5 | K74: =I74*J74 -> 5850
A75: 45374 | B75: 64号 | C75: 45374 | F75: 二甲苯 | G75: 1 | H75: 180 | I75: =G75*H75 -> 180 | J75: 8.1 | K75: =I75*J75 -> 1458
A76: 45374 | B76: 64号 | C76: 45374 | F76: 730浆加工费 | G76: 1 | H76: =SUM(H73:H75) -> 1280 | I76: =G76*H76 -> 1280 | J76: 0.8 | K76: =I76*J76 -> 1024 | L76: =SUM(K69:K76) -> 14116
A77: 45376 | B77: 65号 | C77: 45374 | F77: 108树脂：自备 | G77: 1 | H77: 50 | I77: =G77*H77 -> 50
A78: 45376 | B78: 65号 | C78: 45374 | F78: 14分散剂：自备 | G78: 1 | H78: 6 | I78: =G78*H78 -> 6
A79: 45376 | B79: 65号 | C79: 45374 | F79: 防尘浆：自备 | G79: 1 | H79: 1.5 | I79: =G79*H79 -> 1.5
A80: 45376 | B80: 65号 | C80: 45374 | F80: 酞蓝粉：：自备 | G80: 1 | H80: 25 | I80: =G80*H80 -> 25
A81: 45376 | B81: 65号 | C81: 45374 | F81: 丁酯 | G81: 1 | H81: 57 | I81: =G81*H81 -> 57 | J81: 8.2 | K81: =I81*J81 -> 467.4 | L81: 损耗：17.5KG
A82: 45376 | B82: 65号 | C82: 45374 | F82: 二甲苯 | G82: 1 | H82: 58 | I82: =G82*H82 -> 58 | J82: 8.1 | K82: =I82*J82 -> 469.8 | L82: 净重：180KG
A83: 45376 | B83: 65号 | C83: 45374 | F83: 酞青蓝浆加工费 | G83: 1 | H83: =SUM(H77:H82) -> 197.5 | I83: =G83*H83 -> 197.5 | J83: 5 | K83: =I83*J83 -> 987.5
A84: 45376 | B84: 65号 | C84: 45375 | F84: 贾总借20L白大口桶 | G84: 30 | H84: 1 | I84: =G84*H84 -> 30 | J84: 12.5 | K84: =I84*J84 -> 375 | L84: =SUM(K77:K84) -> 2299.7
F85: 从3月26日起漆类配方均已调整
A86: 45378 | B86: 77号 | C86: 45377 | F86: 108树脂：自备（三木） | G86: 1 | H86: 150 | I86: =G86*H86 -> 150
A87: 45378 | B87: 77号 | C87: 45377 | F87: 环己酮: | G87: 1 | H87: 105 | I87: =G87*H87 -> 105 | J87: 10.3 | K87: =I87*J87 -> 1081.5
A88: 45378 | B88: 77号 | C88: 45377 | F88: 715浆：自备 | G88: 1 | H88: 85 | I88: =G88*H88 -> 85 | L88: ABS光油：
A89: 45378 | B89: 77号 | C89: 45377 | F89: 730浆：自备 | G89: 1 | H89: 160 | I89: =G89*H89 -> 160 | M89: 商标：ABS光油/重量：17±0.1KG
A90: 45378 | B90: 77号 | C90: 45377 | F90: ABS光油加工费 | G90: 1 | H90: =SUM(H86:H89) -> 500 | I90: =G90*H90 -> 500 | J90: 1 | K90: =I90*J90 -> 500 | L90: =SUM(K86:K90) -> 1581.5
A91: 45380 | B91: 79号 | C91: 45378 | F91: 聚酮浆：自备 | G91: 1 | H91: 75 | I91: =G91*H91 -> 75
A92: 45380 | B92: 79号 | C92: 45378 | F92: 808 | G92: 1 | H92: 112.5 | I92: =G92*H92 -> 112.5 | J92: 10.3 | K92: =I92*J92 -> 1158.75
A93: 45380 | B93: 79号 | C93: 45378 | F93: 聚酮液加工费 | G93: 1 | H93: =SUM(H91:H92) -> 187.5 | I93: =G93*H93 -> 187.5 | J93: 1 | K93: =I93*J93 -> 187.5
A94: 45380 | B94: 79号 | C94: 45378 | F94: 购亮光固化剂 | G94: 1 | H94: 20 | I94: =G94*H94 -> 20 | J94: 15.5 | K94: =I94*J94 -> 310
A95: 45380 | B95: 79号 | C95: 3月27、28 | F95: 购包装：20L白大口 | G95: 38 | H95: 1 | I95: =G95*H95 -> 38 | J95: 12.5 | K95: =I95*J95 -> 475 | L95: =SUM(K91:K95) -> 2131.25
A96: 45380 | B96: 80号 | C96: 45378 | F96: 108树脂：自备 | G96: 1 | H96: 100 | I96: =G96*H96 -> 100
A97: 45380 | B97: 80号 | C97: 45378 | F97: 中黄浆:自备 | G97: 1 | H97: 110 | I97: =G97*H97 -> 110
A98: 45380 | B98: 80号 | C98: 45378 | F98: 715浆：自备 | G98: 1 | H98: 35 | I98: =G98*H98 -> 35
A99: 45380 | B99: 80号 | C99: 45378 | F99: 730浆：自备 | G99: 1 | H99: 160 | I99: =G99*H99 -> 160
A100: 45380 | B100: 80号 | C100: 45378 | F100: 聚酮液：自备 | G100: 1 | H100: 62.5 | I100: =G100*H100 -> 62.5 | L100: 18KG/桶
...

Sheet 25出货
A1: 2月 | B1: 25年2月起加工金额合计 | E1: =K1+K67+K291+K564+K712+K943+K1109+K1186+K1356+K1514 -> 490046.28 | F1: 25年2月加工费总计 | G1: =O1+O67+O291+O564+O712+O943+O1109+O1186+O1356+O1514 -> 167177.45 | J1: 金额总计 | K1: =SUM(K4:K65) -> 8954.284 | L1: 李总材料金额 | M1: =材料!L299 -> 4650.334 | N1: 加工费 | O1: =K11+K19+K26+K33+K38+K43+K51+K60+K65 -> 4237.55 | P1: 成品
J2: 加工吨位 | L2: 包装桶金额 | M2: =K27+K44 -> 64 | N2: 总金额 | O2: =M1+M2+O1+Q1 -> 8951.884
A3: 日期 | B3: 单号 | C3: 产品型号 | F3: 产品名称 | G3: 数量/件 | H3: 规格/KG | I3: 数量/KG | J3: 单价/元 | K3: 金额/元 | L3: 备注 | M3: 金额合计
A4: 45706 | B4: 13号 | C4: 45706 | F4: 108树脂：自备 | G4: 1 | H4: 99.5 | I4: =G4*H4 -> 99.5
A5: 45707 | B5: 13号 | C5: 45706 | F5: 1#浆 | G5: 1 | H5: 154.5 | I5: =G5*H5 -> 154.5
A6: 45707 | B6: 13号 | C6: 45706 | F6: 3#浆 | G6: 1 | H6: 39 | I6: =G6*H6 -> 39
A7: 45707 | B7: 13号 | C7: 45706 | F7: 中黄浆：自备 | G7: 1 | H7: 110 | I7: =G7*H7 -> 110 | L7: 18KG/桶
A8: 45707 | B8: 13号 | C8: 45706 | F8: 聚酮液：自备 | G8: 1 | H8: 55 | I8: =G8*H8 -> 55
A9: 45707 | B9: 13号 | C9: 45706 | F9: 808 | G9: 1 | H9: 28.5 | I9: =G9*H9 -> 28.5 | J9: 10 | K9: =I9*J9 -> 285
A10: 45707 | B10: 13号 | C10: 45706 | F10: 807+ | G10: 1 | H10: 65.5 | I10: =G10*H10 -> 65.5 | J10: 6.2 | K10: =I10*J10 -> 406.1
A11: 45707 | B11: 13号 | C11: 45706 | F11: ABS亮黄加工费 | G11: 1 | H11: =SUM(H4:H10) -> 552 | I11: =G11*H11 -> 552 | J11: 1 | K11: =I11*J11 -> 552 | L11: =SUM(K4:K11) -> 1243.1
A12: 45707 | B12: 14号 | C12: 45706 | F12: 108树脂：自备 | G12: 1 | H12: 90 | I12: =G12*H12 -> 90
A13: 45707 | B13: 14号 | C13: 45706 | F13: 5R大红浆：自备 | G13: 1 | H13: 90 | I13: =G13*H13 -> 90
A14: 45707 | B14: 14号 | C14: 45706 | F14: 3号浆：自备 | G14: 1 | H14: 128 | I14: =G14*H14 -> 128
A15: 45707 | B15: 14号 | C15: 45706 | F15: 808 | G15: 1 | H15: 60 | I15: =G15*H15 -> 60 | J15: 10 | K15: =I15*J15 -> 600 | L15: 17KG/桶（除白桶18KG*5桶）
A16: 45707 | B16: 14号 | C16: 45706 | F16: 807+ | G16: 1 | H16: 130 | I16: =G16*H16 -> 130 | J16: 6.2 | K16: =I16*J16 -> 806 | L16: =SUBTOTAL(9,#REF!) -> #REF!
A17: 45707 | B17: 14号 | C17: 45706 | F17: 807A | G17: 1 | H17: 12 | I17: =G17*H17 -> 12 | J17: 7.8 | K17: =I17*J17 -> 93.6
A18: 45707 | B18: 14号 | C18: 45706 | F18: 聚酮液 | G18: 1 | H18: 90 | I18: =G18*H18 -> 90
A19: 45707 | B19: 14号 | C19: 45706 | F19: 大红普加工费 | G19: 1 | H19: =SUM(H12:H18) -> 600 | I19: =G19*H19 -> 600 | J19: 1 | K19: =I19*J19 -> 600 | L19: =SUM(K12:K19) -> 2099.6
A20: 45710 | B20: 35号 | C20: 45709 | F20: 亮黄成品 | G20: 1 | H20: 673 | I20: =G20*H20 -> 673
A21: 45710 | B21: 35号 | C21: 45709 | F21: 6920防尘浆 | G21: 1 | H21: 3 | I21: =G21*H21 -> 3
A22: 45710 | B22: 35号 | C22: 45709 | F22: 106D | G22: 1 | H22: 20.5 | I22: =G22*H22 -> 20.5 | J22: 17 | K22: =I22*J22 -> 348.5 | M22: 加0.5
A23: 45710 | B23: 35号 | C23: 45709 | F23: 3000目重钙 | G23: 1 | H23: 65 | I23: =G23*H23 -> 65 | J23: 0.9 | K23: =I23*J23 -> 58.5 | L23: 18KG/桶 | M23: 加2.0
A24: 45710 | B24: 35号 | C24: 45709 | F24: 812+ | G24: 1 | H24: 4 | I24: =G24*H24 -> 4 | J24: 3.7 | K24: =I24*J24 -> 14.8 | M24: 加0.2
A25: 45710 | B25: 35号 | C25: 45709 | F25: 807+ | G25: 1 | H25: 4.5 | I25: =G25*H25 -> 4.5 | J25: 6.2 | K25: =I25*J25 -> 27.9
A26: 45710 | B26: 35号 | C26: 45709 | F26: 哑黄加工费 | G26: 1 | H26: =SUM(H20:H25) -> 770 | I26: =G26*H26 -> 770 | J26: 1 | K26: =I26*J26 -> 770
A27: 45710 | B27: 35号 | C27: 45709 | F27: 自提黑色浆包装 | G27: 4 | H27: 1 | I27: =G27*H27 -> 4 | J27: 12.5 | K27: =I27*J27 -> 50 | L27: =SUM(K20:K27) -> 1269.7
A28: 45710 | B28: 36号 | C28: 45710 | F28: 108树脂：自备 | G28: 1 | H28: 48 | I28: =G28*H28 -> 48
A29: 45710 | B29: 36号 | C29: 45710 | F29: 5014B:自备 | G29: 1 | H29: 4.5 | I29: =G29*H29 -> 4.5
A30: 45710 | B30: 36号 | C30: 45710 | F30: 996 | G30: 1 | H30: 150 | I30: =G30*H30 -> 150
A31: 45710 | B31: 36号 | C31: 45710 | F31: 807A | G31: 1 | H31: 30 | I31: =G31*H31 -> 30 | J31: 7.8 | K31: =I31*J31 -> 234
A32: 45710 | B32: 36号 | C32: 45710 | F32: 802A | G32: 1 | H32: 30 | I32: =G32*H32 -> 30 | J32: 7.8 | K32: =I32*J32 -> 234
A33: 45710 | B33: 36号 | C33: 45710 | F33: 白浆加工费 | G33: 1 | H33: =SUM(H28:H32) -> 262.5 | I33: =G33*H33 -> 262.5 | J33: 3 | K33: =I33*J33 -> 787.5 | L33: =SUM(K28:K33) -> 1255.5
A34: 45710 | B34: 37号 | C34: 45710 | F34: 108树脂：自备 | G34: 1 | H34: 24 | I34: =G34*H34 -> 24
A35: 45710 | B35: 37号 | C35: 45710 | F35: 996 | G35: 1 | H35: 75 | I35: =G35*H35 -> 75
A36: 45710 | B36: 37号 | C36: 45710 | F36: 807A | G36: 1 | H36: 15 | I36: =G36*H36 -> 15 | J36: 7.8 | K36: =I36*J36 -> 117
A37: 45710 | B37: 37号 | C37: 45710 | F37: 802A | G37: 1 | H37: 15 | I37: =G37*H37 -> 15 | J37: 7.8 | K37: =I37*J37 -> 117
A38: 45710 | B38: 37号 | C38: 45710 | F38: 白浆加工费 | G38: 1 | H38: =SUM(H34:H37) -> 129 | I38: =G38*H38 -> 129 | J38: 3 | K38: =I38*J38 -> 387 | L38: =SUM(K34:K38) -> 621
A39: 45712 | B39: 39号 | C39: 2月22、24 | F39: 108树脂：自备 | G39: 1 | H39: 50 | I39: =G39*H39 -> 50 | J39: 13.6
A40: 45712 | B40: 39号 | C40: 2月22、24 | F40: 5RK大红粉 | G40: 1 | H40: 25 | I40: =G40*H40 -> 25 | J40: 49 | L40: 23.2/KG
A41: 45712 | B41: 39号 | C41: 2月22、24 | F41: 808* | G41: 1 | H41: 45 | I41: =G41*H41 -> 45 | J41: 10 | K41: =I41*J41 -> 450 | L41: 152=170-18损耗
A42: 45712 | B42: 39号 | C42: 2月22、24 | F42: 807+ | G42: 1 | H42: 50 | I42: =G42*H42 -> 50 | J42: 6.2 | K42: =I42*J42 -> 310
A43: 45712 | B43: 39号 | C43: 2月22、24 | F43: 5RK大红浆加工费 | G43: 1 | H43: =SUM(H39:H42) -> 170 | I43: =G43*H43 -> 170 | J43: 5 | K43: =I43*J43 -> 850 | L43: =SUM(K39:K43) -> 1610
A44: 45712 | B44: 39号 | C44: 2月22、24 | F44: 自提大红、白浆包装5L | G44: 2 | H44: 1 | I44: =G44*H44 -> 2 | J44: 7 | K44: =I44*J44 -> 14 | L44: 18KG*4桶
A45: 45714 | B45: 44号 | C45: 45714 | F45: 108树脂：自备 | G45: 1 | H45: 7.65 | I45: =G45*H45 -> 7.65
A46: 45714 | B46: 44号 | C46: 45714 | F46: 5RK大红浆 | G46: 1 | H46: 7.65 | I46: =G46*H46 -> 7.65
A47: 45714 | B47: 44号 | C47: 45714 | F47: 3#浆：自备 | G47: 1 | H47: 10.88 | I47: =G47*H47 -> 10.88
A48: 45714 | B48: 44号 | C48: 45714 | F48: 聚酮液 | G48: 1 | H48: 7.65 | I48: =G48*H48 -> 7.65
A49: 45714 | B49: 44号 | C49: 45714 | F49: 808* | G49: 1 | H49: 5.1 | I49: =G49*H49 -> 5.1 | J49: 10 | K49: =I49*J49 -> 51 | L49: 17KG/桶
A50: 45714 | B50: 44号 | C50: 45714 | F50: 807+ | G50: 1 | H50: 12.07 | I50: =G50*H50 -> 12.07 | J50: 6.2 | K50: =I50*J50 -> 74.834
A51: 45714 | B51: 44号 | C51: 45714 | F51: 亮大红加工费 | G51: 1 | H51: =SUM(H45:H50) -> 51 | I51: =G51*H51 -> 51 | J51: 1 | K51: =I51*J51 -> 51 | L51: =SUM(K45:K51) -> 176.834
A52: 45714 | B52: 45号 | C52: 45714 | F52: 108树脂：自备（夏） | G52: 1 | H52: 10.8 | I52: =G52*H52 -> 10.8
A53: 45714 | B53: 45号 | C53: 45714 | F53: 白浆：自备 | G53: 1 | H53: 10.8 | I53: =G53*H53 -> 10.8
A54: 45714 | B54: 45号 | C54: 45714 | F54: 2#浆 | G54: 1 | H54: 2.75 | I54: =G54*H54 -> 2.75
A55: 45714 | B55: 45号 | C55: 45714 | F55: 3#浆 | G55: 1 | H55: 11.6 | I55: =G55*H55 -> 11.6 | L55: 18KG/桶 | M55: 商标：已打印（去掉普字）
A56: 45714 | B56: 45号 | C56: 45714 | F56: 聚酮液：自备 | G56: 1 | H56: 6.75 | I56: =G56*H56 -> 6.75
A57: 45714 | B57: 45号 | C57: 45714 | F57: 808 | G57: 1 | H57: 1.35 | I57: =G57*H57 -> 1.35 | J57: 10 | K57: =I57*J57 -> 13.5
A58: 45714 | B58: 45号 | C58: 45714 | F58: 802A | G58: 1 | H58: 2.5 | I58: =G58*H58 -> 2.5 | J58: 7.8 | K58: =I58*J58 -> 19.5 | L58: 18KG/桶
A59: 45714 | B59: 45号 | C59: 45714 | F59: 807+ | G59: 1 | H59: 7.5 | I59: =G59*H59 -> 7.5 | J59: 6.2 | K59: =I59*J59 -> 46.5
A60: 45714 | B60: 45号 | C60: 45714 | F60: 亮白（普）加工费 | G60: 1 | H60: =SUM(H52:H59) -> 54.05 | I60: =G60*H60 -> 54.05 | J60: 1 | K60: =I60*J60 -> 54.05 | L60: =SUM(K52:K60) -> 133.55
A61: 45715 | B61: 46号 | C61: 45715 | F61: 橡皮漆底黑成品 | G61: 1 | H61: 120 | I61: =G61*H61 -> 120
A62: 45715 | B62: 46号 | C62: 45715 | F62: C311黑浆:自备 | G62: 1 | H62: 6 | I62: =G62*H62 -> 6
A63: 45715 | B63: 46号 | C63: 45715 | F63: 802A | G63: 1 | H63: 30 | I63: =G63*H63 -> 30 | J63: 7.8 | K63: =I63*J63 -> 234
A64: 45715 | B64: 46号 | C64: 45715 | F64: 812+ | G64: 1 | H64: 30 | I64: =G64*H64 -> 30 | J64: 3.7 | K64: =I64*J64 -> 111
A65: 45715 | B65: 46号 | C65: 45715 | F65: 橡皮漆底黑加工费 | G65: 1 | H65: =SUM(H61:H64) -> 186 | I65: =G65*H65 -> 186 | J65: 1 | K65: =I65*J65 -> 186 | L65: =SUM(K62:K65) -> 531
F66: 亮白多打印了1缸、亮黄、哑黄、大红、橡皮漆底黑、优特黑、烤漆黑一缸商标已打印
A67: 3月 | J67: 金额总计 | K67: =SUM(K70:K289) -> 69508.15 | L67: 李总材料金额 | M67: =材料!L264+K129+K245 -> 41888.85 | N67: 加工费 | O67: =K81+K88+K98+K107+K114+K120+K132+K139+K144+K152+K161+K167+K178+K188+K195+K206+K214+K219+K224+K232+K243+K259+K254+K264+K277+K288 -> 21768.8 | P67: 成品 | Q67: =K70+K123+K124+K125+K126+K127+K196+K197+K244+K265+K266+K267+K268+K289 -> 5368
J68: 加工吨位 | L68: 包装桶金额 | M68: =K99+K108+K115+K128+K198+K269+K270 -> 482.5 | N68: 总金额 | O68: =M67+M68+O67+Q67 -> 69508.15
A69: 日期 | B69: 单号 | C69: 产品型号 | F69: 产品名称 | G69: 数量/件 | H69: 规格/KG | I69: 数量/KG | J69: 单价/元 | K69: 金额/元 | L69: 备注 | M69: 金额合计
A70: 45722 | B70: 19号 | C70: 45721 | F70: 购亮光白面 | G70: 2 | H70: 10 | I70: =G70*H70 -> 20 | J70: 18 | K70: =I70*J70 -> 360 | L70: 含包装（GAA:7.5KG+2.5KG白浆/桶）
A71: 45722 | B71: 19号 | C71: 45721 | F71: 108树脂：自备（三木） | G71: 1 | H71: 100 | I71: =G71*H71 -> 100
A72: 45722 | B72: 19号 | C72: 45721 | F72: 白浆:自备 | G72: 1 | H72: 200 | I72: =G72*H72 -> 200
A73: 45722 | B73: 19号 | C73: 45721 | F73: 715浆：自备 | G73: 1 | H73: 42 | I73: =G73*H73 -> 42
A74: 45722 | B74: 19号 | C74: 45721 | F74: 2#浆：自备 | G74: 1 | H74: 69 | I74: =G74*H74 -> 69
A75: 45722 | B75: 19号 | C75: 45721 | F75: 120浆：自备 | G75: 1 | H75: 115 | I75: =G75*H75 -> 115
A76: 45722 | B76: 19号 | C76: 45721 | F76: 3#浆：自备 | G76: 1 | H76: 79 | I76: =G76*H76 -> 79
A77: 45722 | B77: 19号 | C77: 45721 | F77: 106D哑粉 | G77: 1 | H77: 25 | I77: =G77*H77 -> 25 | J77: 17 | K77: =I77*J77 -> 425
A78: 45722 | B78: 19号 | C78: 45721 | F78: 812+ | G78: 1 | H78: 370 | I78: =G78*H78 -> 370 | J78: 3.7 | K78: =I78*J78 -> 1369
A79: 45722 | B79: 19号 | C79: 45721 | F79: 3000目重钙 | G79: 1 | H79: 50 | I79: =G79*H79 -> 50 | J79: 0.9 | K79: =I79*J79 -> 45 | L79: 18KG/桶
A80: 45722 | B80: 19号 | C80: 45721 | F80: 防尘浆:自备 | G80: 1 | H80: 2.5 | I80: =G80*H80 -> 2.5
A81: 45722 | B81: 19号 | C81: 45721 | F81: 哑白（普）加工费 | G81: 1 | H81: =SUM(H71:H80) -> 1052.5 | I81: =G81*H81 -> 1052.5 | J81: 1 | K81: =I81*J81 -> 1052.5 | L81: =SUM(K70:K81) -> 3251.5
F82: 以上商标均已打印（除元月烤漆黑一缸未打印外）
F83: 红色浆磨第二次加仲丁酯5KG未开单
A84: 45726 | B84: 33号 | C84: 45726 | F84: 108树脂：自备 | G84: 1 | H84: 48 | I84: =G84*H84 -> 48
A85: 45726 | B85: 33号 | C85: 45726 | F85: 996 | G85: 1 | H85: 150 | I85: =G85*H85 -> 150
A86: 45726 | B86: 33号 | C86: 45726 | F86: 807A | G86: 1 | H86: 30 | I86: =G86*H86 -> 30 | J86: 7.8 | K86: =I86*J86 -> 234
A87: 45726 | B87: 33号 | C87: 45726 | F87: 802A | G87: 1 | H87: 30 | I87: =G87*H87 -> 30 | J87: 7.8 | K87: =I87*J87 -> 234
A88: 45726 | B88: 33号 | C88: 45726 | F88: 白浆加工费 | G88: 1 | H88: =SUM(H84:H87) -> 258 | I88: =G88*H88 -> 258 | J88: 3 | K88: =I88*J88 -> 774
A89: 45726 | B89: 33号 | C89: 45721 | F89: 5RK大红浆磨第二次：807+ | G89: 1 | H89: 5 | I89: =G89*H89 -> 5 | J89: 6.4 | K89: =I89*J89 -> 32 | L89: =SUM(K84:K89) -> 1274
A90: 45727 | B90: 38号 | C90: 45727 | F90: 108树脂：自备（夏） | G90: 1 | H90: 240 | I90: =G90*H90 -> 240
A91: 45727 | B91: 38号 | C91: 45727 | F91: 白浆：自备 | G91: 1 | H91: 240 | I91: =G91*H91 -> 240
A92: 45727 | B92: 38号 | C92: 45727 | F92: 1#浆 | G92: 1 | H92: 61 | I92: =G92*H92 -> 61
A93: 45727 | B93: 38号 | C93: 45727 | F93: 3#浆 | G93: 1 | H93: 257 | I93: =G93*H93 -> 257 | L93: 18KG/桶 | M93: 商标：已打印（去掉普字）
A94: 45727 | B94: 38号 | C94: 45727 | F94: 聚酮液：自备 | G94: 1 | H94: 150 | I94: =G94*H94 -> 150 | L94: 白桶：18KG*10桶发货
A95: 45727 | B95: 38号 | C95: 45727 | F95: 808 | G95: 1 | H95: 30 | I95: =G95*H95 -> 30 | J95: 10 | K95: =I95*J95 -> 300
A96: 45727 | B96: 38号 | C96: 45727 | F96: 802A | G96: 1 | H96: 83 | I96: =G96*H96 -> 83 | J96: 7.8 | K96: =I96*J96 -> 647.4
A97: 45727 | B97: 38号 | C97: 45727 | F97: 807+ | G97: 1 | H97: 139 | I97: =G97*H97 -> 139 | J97: 6.4 | K97: =I97*J97 -> 889.6
A98: 45727 | B98: 38号 | C98: 45727 | F98: 亮白（普）加工费 | G98: 1 | H98: =SUM(H90:H97) -> 1200 | I98: =G98*H98 -> 1200 | J98: 1 | K98: =I98*J98 -> 1200 | O98: 11/3日亮白较以前的实际加量多加了23斤802 | S98: 亮白多2桶已放好，下次少2桶
A99: 45727 | B99: 38号 | C99: 45727 | F99: 另加包装费20L:白大口 | G99: 10 | H99: 1 | I99: =G99*H99 -> 10 | J99: 12.5 | K99: =I99*J99 -> 125 | L99: =SUM(K90:K99) -> 3162 | O99: 11/3烤漆黑较以前的实际加量多加了多加了75斤802
A100: 45727 | B100: 39号 | C100: 45727 | F100: 108树脂：自备（夏） | G100: 1 | H100: 200 | I100: =G100*H100 -> 200
...

Sheet 材料
A1: 26年01月贾材料明细表 | G1: 李总材料金额合计 | L1: =F21+I21+L21+O21+R21+U21+X21+AA21+AD21+AG21+AJ21+AM21+AP21 -> 1561.4
A2: 日期 | B2: 摘要 | D2: 996钛白粉 | G2: 3000目 | J2: 106D、100C是红色字体 | M2: 7025浆：银粉 | P2: 20000分散 | S2: 8333:红色字体是已稀的 | V2: 防尘浆 | Y2: 808 | AB2: 807+ | AE2: 812+ | AH2: 816 | AK2: 802A | AN2: 807A
B3: 品名 | C3: 生产量/KG | D3: 数量 | E3: 单价 | F3: 金额 | G3: 数量 | H3: 单价 | I3: 金额 | J3: 数量 | K3: 单价 | L3: 金额 | M3: 数量 | N3: 单价 | O3: 金额 | P3: 数量 | Q3: 单价 | R3: 金额 | S3: 数量 | T3: 单价 | U3: 金额 | V3: 数量 | W3: 单价 | X3: 金额 | Y3: 数量 | Z3: 单价 | AA3: 金额 | AB3: 数量 | AC3: 单价 | AD3: 金额 | AE3: 数量 | AF3: 单价 | AG3: 金额 | AH3: 数量 | AI3: 单价 | AJ3: 金额 | AK3: 数量 | AL3: 单价 | AM3: 金额 | AN3: 数量 | AO3: 单价 | AP3: 金额
A4: 46025 | B4: 优特黑101A | C4: 1000 | Y4: 50 | Z4: 7.1 | AA4: =Y4*Z4 -> 355 | AK4: 124 | AL4: 6.1 | AM4: =AK4*AL4 -> 756.4 | AN4: 75 | AO4: 6 | AP4: =AN4*AO4 -> 450
C21: =SUM(C4:C20) -> 1000 | D21: =SUM(D4:D20) -> 0 | F21: =SUM(F4:F20) -> 0 | G21: =SUM(G4:G20) -> 0 | I21: =SUM(I4:I20) -> 0 | J21: =SUM(J4:J20) -> 0 | L21: =SUM(L4:L20) -> 0 | M21: =SUM(M4:M20) -> 0 | O21: =SUM(O4:O20) -> 0 | P21: =SUM(P4:P20) -> 0 | R21: =SUM(R4:R20) -> 0 | S21: =SUM(S4:S20) -> 0 | U21: =SUM(U4:U20) -> 0 | V21: =SUM(V4:V20) -> 0 | X21: =SUM(X4:X20) -> 0 | Y21: =SUM(Y4:Y20) -> 50 | AA21: =SUM(AA4:AA20) -> 355 | AB21: =SUM(AB4:AB20) -> 0 | AD21: =SUM(AD4:AD20) -> 0 | AE21: =SUM(AE4:AE20) -> 0 | AG21: =SUM(AG4:AG20) -> 0 | AH21: =SUM(AH4:AH20) -> 0 | AJ21: =SUM(AJ4:AJ20) -> 0 | AK21: =SUM(AK4:AK20) -> 124 | AM21: =SUM(AM4:AM20) -> 756.4 | AN21: =SUM(AN4:AN20) -> 75 | AP21: =SUM(AP4:AP20) -> 450
A23: 25年12月贾材料明细表 | G23: 李总材料金额合计 | L23: =F43+I43+L43+O43+R43+U43+X43+AA43+AD43+AG43+AJ43+AM43+AP43 -> 25383.25
A24: 日期 | B24: 摘要 | D24: 996钛白粉 | G24: 3000目 | J24: 106D、100C是红色字体 | M24: 7025浆：银粉 | P24: 20000分散 | S24: 8333:红色字体是已稀的 | V24: 防尘浆 | Y24: 808 | AB24: 807+ | AE24: 812+ | AH24: 816 | AK24: 802A | AN24: 807A
B25: 品名 | C25: 生产量/KG | D25: 数量 | E25: 单价 | F25: 金额 | G25: 数量 | H25: 单价 | I25: 金额 | J25: 数量 | K25: 单价 | L25: 金额 | M25: 数量 | N25: 单价 | O25: 金额 | P25: 数量 | Q25: 单价 | R25: 金额 | S25: 数量 | T25: 单价 | U25: 金额 | V25: 数量 | W25: 单价 | X25: 金额 | Y25: 数量 | Z25: 单价 | AA25: 金额 | AB25: 数量 | AC25: 单价 | AD25: 金额 | AE25: 数量 | AF25: 单价 | AG25: 金额 | AH25: 数量 | AI25: 单价 | AJ25: 金额 | AK25: 数量 | AL25: 单价 | AM25: 金额 | AN25: 数量 | AO25: 单价 | AP25: 金额
A26: 45993 | B26: 电镀大红 | C26: 200 | Y26: 40 | Z26: 7.5 | AA26: =Y26*Z26 -> 300 | AN26: 23 | AO26: 5.9 | AP26: =AN26*AO26 -> 135.7
A27: 45997 | B27: 优特黑101A | C27: 1000 | Y27: 50 | Z27: 7.5 | AA27: =Y27*Z27 -> 375 | AK27: 155 | AL27: 6.1 | AM27: =AK27*AL27 -> 945.5 | AN27: 95 | AO27: 5.9 | AP27: =AN27*AO27 -> 560.5 | AQ27: 125
A28: 46000 | B28: 中黄浆 | C28: 225 | Y28: 25 | Z28: 7.5 | AA28: =Y28*Z28 -> 187.5 | AN28: 25 | AO28: 5.9 | AP28: =AN28*AO28 -> 147.5 | AQ28: 98
A29: 46000 | B29: 亮黄 | C29: 502.5 | Y29: 26 | Z29: 7.5 | AA29: =Y29*Z29 -> 195 | AN29: 61 | AO29: 5.9 | AP29: =AN29*AO29 -> 359.9 | AQ29: 25
A30: 46001 | B30: C311黑色浆 | C30: 750 | P30: 25 | Q30: 82 | R30: =P30*Q30 -> 2050 | Y30: 300 | Z30: 7.5 | AA30: =Y30*Z30 -> 2250 | AB30: 125 | AC30: 5 | AD30: =AB30*AC30 -> 625 | AQ30: 50
A31: 46002 | B31: 优特黑101A | C31: 1000 | Y31: 50 | Z31: 7.5 | AA31: =Y31*Z31 -> 375 | AH31: 5 | AI31: 2.9 | AJ31: =AH31*AI31 -> 14.5 | AK31: 155 | AL31: 6.1 | AM31: =AK31*AL31 -> 945.5 | AN31: 95 | AO31: 5.9 | AP31: =AN31*AO31 -> 560.5 | AQ31: 79
A32: 46006 | B32: 亮大红 | C32: 500 | Y32: 50 | Z32: 7.5 | AA32: =Y32*Z32 -> 375 | AB32: 98 | AC32: 5 | AD32: =AB32*AC32 -> 490 | AN32: 20 | AO32: 5.9 | AP32: =AN32*AO32 -> 118 | AQ32: 1300
A33: 46014 | B33: 柠檬黄漆 | C33: 445 | Y33: 53 | Z33: 7.1 | AA33: =Y33*Z33 -> 376.3 | AB33: 25 | AC33: 5.1 | AD33: =AB33*AC33 -> 127.5 | AN33: 32 | AO33: 5.9 | AP33: =AN33*AO33 -> 188.8 | AQ33: 61
A34: 46014 | B34: 甲苯胺紫红浆 | C34: 172 | Y34: 45 | Z34: 7.1 | AA34: =Y34*Z34 -> 319.5 | AB34: 50 | AC34: 5.1 | AD34: =AB34*AC34 -> 255 | AQ34: 7
A35: 46014 | B35: 哑黄 | C35: 508 | J35: 12 | K35: 17 | L35: =J35*K35 -> 204 | V35: 2 | W35: 25 | X35: =V35*W35 -> 50 | AB35: 79 | AC35: 5.1 | AD35: =AB35*AC35 -> 402.9 | AE35: 55 | AF35: 3 | AG35: =AE35*AF35 -> 165 | AQ35: 45
A36: 46015 | B36: 730浆：17% | C36: 1918 | AB36: 1300 | AC36: 5.1 | AD36: =AB36*AC36 -> 6630 | AN36: 293 | AO36: 5.9 | AP36: =AN36*AO36 -> 1728.7
A37: 46381 | B37: 玫瑰红漆 | C37: 300 | Y37: 30 | Z37: 7.1 | AA37: =Y37*Z37 -> 213 | AB37: 61 | AC37: 5.1 | AD37: =AB37*AC37 -> 311.1 | AK37: 10 | AL37: 6.1 | AM37: =AK37*AL37 -> 61
A38: 46385 | B38: 酞蓝漆 | C38: 172 | Y38: 27 | Z38: 7.1 | AA38: =Y38*Z38 -> 191.7 | AB38: 7 | AC38: 5.1 | AD38: =AB38*AC38 -> 35.7 | AK38: 8 | AL38: 6.1 | AM38: =AK38*AL38 -> 48.8 | AN38: 13 | AO38: 6 | AP38: =AN38*AO38 -> 78
A39: 46386 | B39: 白浆 | C39: 258 | Y39: 30 | Z39: 7.1 | AA39: =Y39*Z39 -> 213 | AN39: 30 | AO39: 6 | AP39: =AN39*AO39 -> 180
A40: 46387 | B40: 哑白 | C40: 1002.5 | J40: 25 | K40: 17 | L40: =J40*K40 -> 425 | V40: 2.5 | W40: 25 | X40: =V40*W40 -> 62.5 | AB40: 45 | AC40: 5.1 | AD40: =AB40*AC40 -> 229.5 | AE40: 239 | AF40: 3 | AG40: =AE40*AF40 -> 717 | AK40: 85 | AL40: 6.2 | AM40: =AK40*AL40 -> 527 | AN40: 30 | AO40: 6 | AP40: =AN40*AO40 -> 180
A41: 46387 | B41: 白裂纹 | C41: 181.5 | J41: 10 | K41: 17 | L41: =J41*K41 -> 170 | AB41: 36.5 | AC41: 5.1 | AD41: =AB41*AC41 -> 186.15 | AE41: 32 | AF41: 3 | AG41: =AE41*AF41 -> 96
C43: =SUM(C26:C42) -> 9134.5 | D43: =SUM(D26:D42) -> 0 | F43: =SUM(F26:F42) -> 0 | G43: =SUM(G26:G42) -> 0 | I43: =SUM(I26:I42) -> 0 | J43: =SUM(J26:J42) -> 47 | L43: =SUM(L26:L42) -> 799 | M43: =SUM(M26:M42) -> 0 | O43: =SUM(O26:O42) -> 0 | P43: =SUM(P26:P42) -> 25 | R43: =SUM(R26:R42) -> 2050 | S43: =SUM(S26:S42) -> 0 | U43: =SUM(U26:U42) -> 0 | V43: =SUM(V26:V42) -> 4.5 | X43: =SUM(X26:X42) -> 112.5 | Y43: =SUM(Y26:Y42) -> 726 | AA43: =SUM(AA26:AA42) -> 5371 | AB43: =SUM(AB26:AB42) -> 1826.5 | AD43: =SUM(AD26:AD42) -> 9292.85 | AE43: =SUM(AE26:AE42) -> 326 | AG43: =SUM(AG26:AG42) -> 978 | AH43: =SUM(AH26:AH42) -> 5 | AJ43: =SUM(AJ26:AJ42) -> 14.5 | AK43: =SUM(AK26:AK42) -> 413 | AM43: =SUM(AM26:AM42) -> 2527.8 | AN43: =SUM(AN26:AN42) -> 717 | AP43: =SUM(AP26:AP42) -> 4237.6
A46: 25年11月贾材料明细表 | G46: 李总材料金额合计 | L46: =F68+I68+L68+O68+R68+U68+X68+AA68+AD68+AG68+AJ68+AM68+AP68 -> 38242.2
A47: 日期 | B47: 摘要 | D47: 996钛白粉 | G47: 3000目 | J47: 106D、100C是红色字体 | M47: 7025浆：银粉 | P47: 20000分散 | S47: 8333:红色字体是已稀的 | V47: 防尘浆 | Y47: 808 | AB47: 807+ | AE47: 812+ | AH47: 811 | AK47: 802A | AN47: 807A
B48: 品名 | C48: 生产量/KG | D48: 数量 | E48: 单价 | F48: 金额 | G48: 数量 | H48: 单价 | I48: 金额 | J48: 数量 | K48: 单价 | L48: 金额 | M48: 数量 | N48: 单价 | O48: 金额 | P48: 数量 | Q48: 单价 | R48: 金额 | S48: 数量 | T48: 单价 | U48: 金额 | V48: 数量 | W48: 单价 | X48: 金额 | Y48: 数量 | Z48: 单价 | AA48: 金额 | AB48: 数量 | AC48: 单价 | AD48: 金额 | AE48: 数量 | AF48: 单价 | AG48: 金额 | AH48: 数量 | AI48: 单价 | AJ48: 金额 | AK48: 数量 | AL48: 单价 | AM48: 金额 | AN48: 数量 | AO48: 单价 | AP48: 金额
A49: 45962 | B49: 亮黄 | C49: 502.5 | Y49: 26 | Z49: 7.6 | AA49: =Y49*Z49 -> 197.6 | AN49: 61 | AO49: 6.1 | AP49: =AN49*AO49 -> 372.1
A50: 45962 | B50: 亮大红 | C50: 500 | Y50: 50 | Z50: 7.6 | AA50: =Y50*Z50 -> 380 | AB50: 95 | AC50: 5.1 | AD50: =AB50*AC50 -> 484.5 | AN50: 10 | AO50: 6.1 | AP50: =AN50*AO50 -> 61
A51: 45966 | B51: 消光剂 | C51: 320 | J51: 40 | K51: 15 | L51: =J51*K51 -> 600 | AB51: 128 | AC51: 5.1 | AD51: =AB51*AC51 -> 652.8 | AK51: 146 | AL51: 6.2 | AM51: =AK51*AL51 -> 905.2
A52: 45967 | B52: 沈阳平光黑 | C52: 364.5 | J52: 8.6 | K52: 17 | L52: =J52*K52 -> 146.2 | V52: 1 | W52: 25 | X52: =V52*W52 -> 25 | Y52: 54 | Z52: 7.6 | AA52: =Y52*Z52 -> 410.4 | AE52: 34 | AF52: 3 | AG52: =AE52*AF52 -> 102 | AK52: 36 | AL52: 6.2 | AM52: =AK52*AL52 -> 223.2 | AN52: 45 | AO52: 6.1 | AP52: =AN52*AO52 -> 274.5
A53: 45969 | B53: 哑红 | C53: 500 | J53: 15 | K53: 17 | L53: =J53*K53 -> 255 | V53: 2 | W53: 25 | X53: =V53*W53 -> 50 | Y53: 47 | Z53: 7.6 | AA53: =Y53*Z53 -> 357.2 | AB53: 51 | AC53: 5.1 | AD53: =AB53*AC53 -> 260.1 | AE53: 30 | AF53: 3 | AG53: =AE53*AF53 -> 90 | AN53: 20 | AO53: 6.1 | AP53: =AN53*AO53 -> 122
A54: 45973 | B54: 黑色浆 | C54: 750 | P54: 25 | Q54: 82 | R54: =P54*Q54 -> 2050 | Y54: 300 | Z54: 7.6 | AA54: =Y54*Z54 -> 2280 | AB54: 125 | AC54: 5.1 | AD54: =AB54*AC54 -> 637.5
A55: 45974 | B55: 平光黑 | C55: 1006 | J55: 30 | K55: 17 | L55: =J55*K55 -> 510 | V55: 3 | W55: 25 | X55: =V55*W55 -> 75 | Y55: 150 | Z55: 7.6 | AA55: =Y55*Z55 -> 1140 | AE55: 75 | AF55: 3 | AG55: =AE55*AF55 -> 225 | AK55: 40 | AL55: 6.2 | AM55: =AK55*AL55 -> 248 | AN55: 117 | AO55: 6.1 | AP55: =AN55*AO55 -> 713.7
A56: 45975 | B56: 优特黑101A-1 | C56: 1000 | Y56: 102 | Z56: 7.6 | AA56: =Y56*Z56 -> 775.2 | AN56: 58 | AO56: 6.1 | AP56: =AN56*AO56 -> 353.8
A57: 45975 | B57: 优特黑101A | C57: 1000 | Y57: 50 | Z57: 7.6 | AA57: =Y57*Z57 -> 380 | AK57: 155 | AL57: 6.2 | AM57: =AK57*AL57 -> 961 | AN57: 95 | AO57: 6.1 | AP57: =AN57*AO57 -> 579.5
A58: 45976 | B58: 白浆 | C58: 344 | Y58: 40 | Z58: 7.6 | AA58: =Y58*Z58 -> 304 | AN58: 40 | AO58: 6.1 | AP58: =AN58*AO58 -> 244
A59: 45978 | B59: 哑白 | C59: 1002.5 | J59: 25 | K59: 17 | L59: =J59*K59 -> 425 | V59: 2.5 | W59: 25 | X59: =V59*W59 -> 62.5 | AB59: 59 | AC59: 5.1 | AD59: =AB59*AC59 -> 300.9 | AE59: 239 | AF59: 3 | AG59: =AE59*AF59 -> 717 | AK59: 30 | AL59: 6.2 | AM59: =AK59*AL59 -> 186 | AN59: 30 | AO59: 6.1 | AP59: =AN59*AO59 -> 183
A60: 45978 | B60: 亮白 | C60: 1200 | Y60: 144 | Z60: 7.6 | AA60: =Y60*Z60 -> 1094.4 | AN60: 186 | AO60: 6.1 | AP60: =AN60*AO60 -> 1134.6
A61: 45981 | B61: 优特黑101A | C61: 1000 | Y61: 50 | Z61: 7.6 | AA61: =Y61*Z61 -> 380 | AK61: 155 | AL61: 6.2 | AM61: =AK61*AL61 -> 961 | AN61: 95 | AO61: 6.1 | AP61: =AN61*AO61 -> 579.5
A62: 11-231 | B62: 优特黑101A-1 | C62: 1000 | Y62: 102 | Z62: 7.6 | AA62: =Y62*Z62 -> 775.2 | AN62: 150 | AO62: 6.1 | AP62: =AN62*AO62 -> 915
A63: 11-20-21* | B63: 5RK大红浆 | C63: 344 | Y63: 90 | Z63: 7.6 | AA63: =Y63*Z63 -> 684 | AB63: 100 | AC63: 5.1 | AD63: =AB63*AC63 -> 510
A64: 45982 | B64: 亮大红 | C64: 500 | Y64: 50 | Z64: 7.6 | AA64: =Y64*Z64 -> 380 | AB64: 98 | AC64: 5.1 | AD64: =AB64*AC64 -> 499.8 | AN64: 20 | AO64: 6.1 | AP64: =AN64*AO64 -> 122
A65: 45986 | B65: 亮大红 | C65: 500 | Y65: 50 | Z65: 7.6 | AA65: =Y65*Z65 -> 380 | AB65: 98 | AC65: 5.1 | AD65: =AB65*AC65 -> 499.8 | AN65: 20 | AO65: 6.1 | AP65: =AN65*AO65 -> 122
A66: 45989 | B66: 715浆：35% | C66: 2850 | AB66: 1400 | AC66: 5.1 | AD66: =AB66*AC66 -> 7140 | AN66: 450 | AO66: 6.1 | AP66: =AN66*AO66 -> 2745
C68: =SUM(C49:C67) -> 14683.5 | D68: =SUM(D49:D67) -> 0 | F68: =SUM(F49:F67) -> 0 | G68: =SUM(G49:G67) -> 0 | I68: =SUM(I49:I67) -> 0 | J68: =SUM(J49:J67) -> 118.6 | L68: =SUM(L49:L67) -> 1936.2 | M68: =SUM(M49:M67) -> 0 | O68: =SUM(O49:O67) -> 0 | P68: =SUM(P49:P67) -> 25 | R68: =SUM(R49:R67) -> 2050 | S68: =SUM(S49:S67) -> 0 | U68: =SUM(U49:U67) -> 0 | V68: =SUM(V49:V67) -> 8.5 | X68: =SUM(X49:X67) -> 212.5 | Y68: =SUM(Y49:Y67) -> 1305 | AA68: =SUM(AA49:AA67) -> 9918 | AB68: =SUM(AB49:AB67) -> 2154 | AD68: =SUM(AD49:AD67) -> 10985.4 | AE68: =SUM(AE49:AE67) -> 378 | AG68: =SUM(AG49:AG67) -> 1134 | AH68: =SUM(AH49:AH67) -> 0 | AJ68: =SUM(AJ49:AJ67) -> 0 | AK68: =SUM(AK49:AK67) -> 562 | AM68: =SUM(AM49:AM67) -> 3484.4 | AN68: =SUM(AN49:AN67) -> 1397 | AP68: =SUM(AP49:AP67) -> 8521.7
A70: 25年10月贾材料明细表 | G70: 李总材料金额合计 | L70: =F95+I95+L95+O95+R95+U95+X95+AA95+AD95+AG95+AJ95+AM95+AP95 -> 31359.07
A71: 日期 | B71: 摘要 | D71: 996钛白粉 | G71: 3000目 | J71: 106D、100C是红色字体 | M71: 7025浆：银粉 | P71: 20000分散 | S71: 8333:红色字体是已稀的 | V71: 防尘浆 | Y71: 808 | AB71: 807+ | AE71: 812+ | AH71: 811 | AK71: 802A | AN71: 807A
B72: 品名 | C72: 生产量/KG | D72: 数量 | E72: 单价 | F72: 金额 | G72: 数量 | H72: 单价 | I72: 金额 | J72: 数量 | K72: 单价 | L72: 金额 | M72: 数量 | N72: 单价 | O72: 金额 | P72: 数量 | Q72: 单价 | R72: 金额 | S72: 数量 | T72: 单价 | U72: 金额 | V72: 数量 | W72: 单价 | X72: 金额 | Y72: 数量 | Z72: 单价 | AA72: 金额 | AB72: 数量 | AC72: 单价 | AD72: 金额 | AE72: 数量 | AF72: 单价 | AG72: 金额 | AH72: 数量 | AI72: 单价 | AJ72: 金额 | AK72: 数量 | AL72: 单价 | AM72: 金额 | AN72: 数量 | AO72: 单价 | AP72: 金额
A73: 45938 | B73: 消光剂 | C73: 160 | J73: 20 | K73: 15 | L73: =J73*K73 -> 300 | AB73: 64 | AC73: 5.5 | AD73: =AB73*AC73 -> 352 | AK73: 73 | AL73: 6.5 | AM73: =AK73*AL73 -> 474.5
A74: 45938 | B74: 白浆 | C74: 258 | Y74: 30 | Z74: 7.6 | AA74: =Y74*Z74 -> 228 | AN74: 30 | AO74: 6.4 | AP74: =AN74*AO74 -> 192
A75: 45940 | B75: ABS光油 | C75: 500 | Y75: 105 | Z75: 7.6 | AA75: =Y75*Z75 -> 798 | AB75: 44 | AC75: 5.4 | AD75: =AB75*AC75 -> 237.6 | AN75: 50 | AO75: 6.4 | AP75: =AN75*AO75 -> 320
A76: 45943 | B76: 沈阳平光黑 | C76: 361 | J76: 10 | K76: 17 | L76: =J76*K76 -> 170 | V76: 1 | W76: 25 | X76: =V76*W76 -> 25 | Y76: 54 | Z76: 7.6 | AA76: =Y76*Z76 -> 410.4 | AE76: 27 | AF76: 3.3 | AG76: =AE76*AF76 -> 89.1 | AK76: 36 | AL76: 6.3 | AM76: =AK76*AL76 -> 226.8 | AN76: 47 | AO76: 6.3 | AP76: =AN76*AO76 -> 296.1
A77: 45944 | B77: 亮大红 | C77: 470 | Y77: 47 | Z77: 7.6 | AA77: =Y77*Z77 -> 357.2 | AB77: 101 | AC77: 5.4 | AD77: =AB77*AC77 -> 545.4 | AN77: 9.4 | AO77: 6.3 | AP77: =AN77*AO77 -> 59.22
A78: 10-14-15 | B78: 黑色浆 | C78: 750 | P78: 25 | Q78: 82 | R78: =P78*Q78 -> 2050 | Y78: 300 | Z78: 7.6 | AA78: =Y78*Z78 -> 2280 | AB78: 125 | AC78: 5.4 | AD78: =AB78*AC78 -> 675
A79: 10-15-16 | B79: 中黄浆 | C79: 225 | Y79: 25 | Z79: 7.6 | AA79: =Y79*Z79 -> 190 | AN79: 25 | AO79: 6.3 | AP79: =AN79*AO79 -> 157.5
A80: 45946 | B80: 优特黑101A | C80: 1000 | Y80: 50 | Z80: 7.6 | AA80: =Y80*Z80 -> 380 | AK80: 155 | AL80: 6.3 | AM80: =AK80*AL80 -> 976.5 | AN80: 95 | AO80: 6.3 | AP80: =AN80*AO80 -> 598.5
A81: 10-16-17 | B81: 柠檬黄浆 | C81: 215 | Y81: 20 | Z81: 7.6 | AA81: =Y81*Z81 -> 152 | AN81: 25 | AO81: 6.3 | AP81: =AN81*AO81 -> 157.5
A82: 45947 | B82: 亮黄 | C82: 502 | Y82: 26 | Z82: 7.6 | AA82: =Y82*Z82 -> 197.6 | AN82: 64.5 | AO82: 6.3 | AP82: =AN82*AO82 -> 406.35
A83: 45950 | B83: 哑白 | C83: 1002.5 | J83: 25 | K83: 17 | L83: =J83*K83 -> 425 | V83: 2.5 | W83: 25 | X83: =V83*W83 -> 62.5 | AB83: 59 | AC83: 5.4 | AD83: =AB83*AC83 -> 318.6 | AE83: 279 | AF83: 3.3 | AG83: =AE83*AF83 -> 920.7 | AK83: 92 | AL83: 6.3 | AM83: =AK83*AL83 -> 579.6
A84: 45951 | B84: 优特黑101A-1 | C84: 1000 | Y84: 102 | Z84: 7.6 | AA84: =Y84*Z84 -> 775.2 | AN84: 150 | AO84: 6.3 | AP84: =AN84*AO84 -> 945
A85: 10-22-23 | B85: 5RK大红浆 | C85: 172.2 | Y85: 72 | Z85: 7.6 | AA85: =Y85*Z85 -> 547.2 | AB85: 80 | AC85: 5.4 | AD85: =AB85*AC85 -> 432
A86: 45954 | B86: 柠檬黄漆 | C86: 184 | Y86: 22 | Z86: 7.6 | AA86: =Y86*Z86 -> 167.2 | AB86: 13 | AC86: 5.4 | AD86: =AB86*AC86 -> 70.2 | AN86: 13 | AO86: 6.3 | AP86: =AN86*AO86 -> 81.9
A87: 45954 | B87: 亮大红 | C87: 500 | Y87: 50 | Z87: 7.6 | AA87: =Y87*Z87 -> 380 | AB87: 108 | AC87: 5.4 | AD87: =AB87*AC87 -> 583.2 | AN87: 10 | AO87: 6.3 | AP87: =AN87*AO87 -> 63
A88: 45955 | B88: 聚酮液 | C88: 750 | Y88: 450 | Z88: 7.6 | AA88: =Y88*Z88 -> 3420
A89: 45955 | B89: 平光黑 | C89: 1000 | J89: 30 | K89: 17 | L89: =J89*K89 -> 510 | V89: 3 | W89: 25 | X89: =V89*W89 -> 75 | Y89: 150 | Z89: 7.6 | AA89: =Y89*Z89 -> 1140 | AE89: 75 | AF89: 3.3 | AG89: =AE89*AF89 -> 247.5 | AK89: 100 | AL89: 6.3 | AM89: =AK89*AL89 -> 630 | AN89: 130 | AO89: 6.3 | AP89: =AN89*AO89 -> 819
A90: 45957 | B90: 白浆 | C90: 258 | Y90: 30 | Z90: 7.6 | AA90: =Y90*Z90 -> 228 | AN90: 30 | AO90: 6.3 | AP90: =AN90*AO90 -> 189
A91: 45961 | B91: 橡皮漆底黑 | C91: 597 | J91: 18 | K91: 17 | L91: =J91*K91 -> 306 | Y91: 66 | Z91: 7.6 | AA91: =Y91*Z91 -> 501.6 | AB91: 175 | AC91: 5.1 | AD91: =AB91*AC91 -> 892.5 | AE91: 144 | AF91: 3 | AG91: =AE91*AF91 -> 432 | AK91: 33 | AL91: 6.3 | AM91: =AK91*AL91 -> 207.9
A92: 45961 | B92: 亮白 | C92: 1200 | Y92: 144 | Z92: 7.6 | AA92: =Y92*Z92 -> 1094.4 | AN92: 166 | AO92: 6.1 | AP92: =AN92*AO92 -> 1012.6
C95: =SUM(C73:C94) -> 11104.7 | D95: =SUM(D73:D94) -> 0 | F95: =SUM(F73:F94) -> 0 | G95: =SUM(G73:G94) -> 0 | I95: =SUM(I73:I94) -> 0 | J95: =SUM(J73:J94) -> 103 | L95: =SUM(L73:L94) -> 1711 | M95: =SUM(M73:M94) -> 0 | O95: =SUM(O73:O94) -> 0 | P95: =SUM(P73:P94) -> 25 | R95: =SUM(R73:R94) -> 2050 | S95: =SUM(S73:S94) -> 0 | U95: =SUM(U73:U94) -> 0 | V95: =SUM(V73:V94) -> 6.5 | X95: =SUM(X73:X94) -> 162.5 | Y95: =SUM(Y73:Y94) -> 1743 | AA95: =SUM(AA73:AA94) -> 13246.8 | AB95: =SUM(AB73:AB94) -> 769 | AD95: =SUM(AD73:AD94) -> 4106.5 | AE95: =SUM(AE73:AE94) -> 525 | AG95: =SUM(AG73:AG94) -> 1689.3 | AH95: =SUM(AH73:AH94) -> 0 | AJ95: =SUM(AJ73:AJ94) -> 0 | AK95: =SUM(AK73:AK94) -> 489 | AM95: =SUM(AM73:AM94) -> 3095.3 | AN95: =SUM(AN73:AN94) -> 844.9 | AP95: =SUM(AP73:AP94) -> 5297.67
A97: 25年9月贾材料明细表 | G97: 李总材料金额合计 | L97: =F121+I121+L121+O121+R121+U121+X121+AA121+AD121+AG121+AJ121+AM121+AP121 -> 27063.74
A98: 日期 | B98: 摘要 | D98: 996钛白粉 | G98: 3000目 | J98: 106D、100C是红色字体 | M98: 7025浆：银粉 | P98: 20000分散 | S98: 8333:红色字体是已稀的 | V98: 防尘浆 | Y98: 808 | AB98: 807+ | AE98: 812+ | AH98: 811 | AK98: 802A | AN98: 807A
B99: 品名 | C99: 生产量/KG | D99: 数量 | E99: 单价 | F99: 金额 | G99: 数量 | H99: 单价 | I99: 金额 | J99: 数量 | K99: 单价 | L99: 金额 | M99: 数量 | N99: 单价 | O99: 金额 | P99: 数量 | Q99: 单价 | R99: 金额 | S99: 数量 | T99: 单价 | U99: 金额 | V99: 数量 | W99: 单价 | X99: 金额 | Y99: 数量 | Z99: 单价 | AA99: 金额 | AB99: 数量 | AC99: 单价 | AD99: 金额 | AE99: 数量 | AF99: 单价 | AG99: 金额 | AH99: 数量 | AI99: 单价 | AJ99: 金额 | AK99: 数量 | AL99: 单价 | AM99: 金额 | AN99: 数量 | AO99: 单价 | AP99: 金额
A100: 45901 | B100: 平光黑 | C100: 1000 | J100: 30 | K100: 17 | L100: =J100*K100 -> 510 | V100: 3 | W100: 25 | X100: =V100*W100 -> 75 | Y100: 150 | Z100: 7.6 | AA100: =Y100*Z100 -> 1140 | AE100: 75 | AF100: 3.2 | AG100: =AE100*AF100 -> 240 | AK100: 100 | AL100: 6.5 | AM100: =AK100*AL100 -> 650 | AN100: 130 | AO100: 6.4 | AP100: =AN100*AO100 -> 832
A101: 45901 | B101: 哑黄 | C101: 550 | G101: 50 | H101: 0.9 | I101: =G101*H101 -> 45 | J101: 15 | K101: 17 | L101: =J101*K101 -> 255 | V101: 2.5 | W101: 25 | X101: =V101*W101 -> 62.5 | AB101: 107.5 | AC101: 5.5 | AD101: =AB101*AC101 -> 591.25 | AE101: 70 | AF101: 3.2 | AG101: =AE101*AF101 -> 224
A102: 45905 | B102: 优特黑101A-1 | C102: 1000 | Y102: 102 | Z102: 7.6 | AA102: =Y102*Z102 -> 775.2 | AN102: 150 | AO102: 6.4 | AP102: =AN102*AO102 -> 960
A103: 45910 | B103: 稀料 | C103: 4 | Y103: 0.7 | Z103: 7.6 | AA103: =Y103*Z103 -> 5.32 | AB103: 1.3 | AC103: 5.5 | AD103: =AB103*AC103 -> 7.15 | AE103: 1.6 | AF103: 3.3 | AG103: =AE103*AF103 -> 5.28 | AN103: 0.4 | AO103: 6.4 | AP103: =AN103*AO103 -> 2.56
A104: 45910 | B104: 消光剂 | C104: 160 | J104: 20 | K104: 15 | L104: =J104*K104 -> 300 | AB104: 64 | AC104: 5.5 | AD104: =AB104*AC104 -> 352 | AK104: 73 | AL104: 6.5 | AM104: =AK104*AL104 -> 474.5
A105: 45912 | B105: 哑白 | C105: 1002.5 | J105: 25 | K105: 17 | L105: =J105*K105 -> 425 | V105: 2.5 | W105: 25 | X105: =V105*W105 -> 62.5 | AB105: 59 | AC105: 5.5 | AD105: =AB105*AC105 -> 324.5 | AE105: 279 | AF105: 3.3 | AG105: =AE105*AF105 -> 920.7 | AK105: 92 | AL105: 6.5 | AM105: =AK105*AL105 -> 598
A106: 45912 | B106: 亮大红 | C106: 500 | Y106: 50 | Z106: 7.6 | AA106: =Y106*Z106 -> 380 | AB106: 108 | AC106: 5.5 | AD106: =AB106*AC106 -> 594 | AN106: 10 | AO106: 6.4 | AP106: =AN106*AO106 -> 64
A107: 45913 | B107: 哑大红 | C107: 553 | G107: 50 | H107: 0.9 | I107: =G107*H107 -> 45 | J107: 15 | K107: 17 | L107: =J107*K107 -> 255 | V107: 2 | W107: 25 | X107: =V107*W107 -> 50 | AB107: 106 | AC107: 5.5 | AD107: =AB107*AC107 -> 583 | AE107: 130 | AF107: 3.3 | AG107: =AE107*AF107 -> 429
A108: 45913 | B108: 玫瑰红漆 | C108: 300 | Y108: 30 | Z108: 7.6 | AA108: =Y108*Z108 -> 228 | AB108: 61 | AC108: 5.5 | AD108: =AB108*AC108 -> 335.5 | AK108: 10 | AL108: 6.5 | AM108: =AK108*AL108 -> 65
A109: 45914 | B109: 消光剂、购哑粉、李购黑色粉30KG(3包）已减 | C109: 160 | J109: 20 | K109: 15 | L109: =J109*K109 -> 300 | AB109: 64 | AC109: 5.5 | AD109: =AB109*AC109 -> 352 | AK109: 73 | AL109: 6.5 | AM109: =AK109*AL109 -> 474.5
A110: 45922 | B110: 购哑粉、白浆 | C110: 258 | Y110: 30 | Z110: 7.6 | AA110: =Y110*Z110 -> 228 | AN110: 30 | AO110: 6.4 | AP110: =AN110*AO110 -> 192
A111: 45923 | B111: 环保亮黄 | C111: 200 | Y111: 28 | Z111: 7.6 | AA111: =Y111*Z111 -> 212.8 | AB111: 16 | AC111: 5.5 | AD111: =AB111*AC111 -> 88
A112: 45923 | B112: 环保哑黄 | C112: 200 | J112: 6 | K112: 17 | L112: =J112*K112 -> 102 | V112: 0.4 | W112: 25 | X112: =V112*W112 -> 10 | AB112: 40 | AC112: 5.5 | AD112: =AB112*AC112 -> 220 | AE112: 31.6 | AF112: 3.3 | AG112: =AE112*AF112 -> 104.28
A113: 45925 | B113: 平光黑、白大口桶 | C113: 1006 | J113: 30 | K113: 17 | L113: =J113*K113 -> 510 | V113: 3 | W113: 25 | X113: =V113*W113 -> 75 | Y113: 150 | Z113: 7.6 | AA113: =Y113*Z113 -> 1140 | AE113: 75 | AF113: 3.3 | AG113: =AE113*AF113 -> 247.5 | AK113: 100 | AL113: 6.5 | AM113: =AK113*AL113 -> 650 | AN113: 130 | AO113: 6.4 | AP113: =AN113*AO113 -> 832
A114: 45925 | B114: 5RK大红浆 | C114: 172 | Y114: 45 | Z114: 7.6 | AA114: =Y114*Z114 -> 342 | AB114: 50 | AC114: 5.5 | AD114: =AB114*AC114 -> 275
A115: 45926 | B115: 亮大红 | C115: 500 | Y115: 50 | Z115: 7.6 | AA115: =Y115*Z115 -> 380 | AB115: 108 | AC115: 5.5 | AD115: =AB115*AC115 -> 594 | AN115: 10 | AO115: 6.4 | AP115: =AN115*AO115 -> 64
A116: 45926 | B116: 优特黑101A-1：2缸 | C116: 2000 | Y116: 204 | Z116: 7.6 | AA116: =Y116*Z116 -> 1550.4 | AN116: 300 | AO116: 6.4 | AP116: =AN116*AO116 -> 1920
A117: 45927 | B117: 亮白 | C117: 1000 | Y117: 120 | Z117: 7.6 | AA117: =Y117*Z117 -> 912 | AN117: 155 | AO117: 6.4 | AP117: =AN117*AO117 -> 992
A118: 45928 | B118: 桃红浆 | C118: 179 | Y118: 36 | Z118: 7.6 | AA118: =Y118*Z118 -> 273.6 | AB118: 40 | AC118: 5.5 | AD118: =AB118*AC118 -> 220 | AN118: 10 | AO118: 6.4 | AP118: =AN118*AO118 -> 64
A119: 45929 | B119: 桃红漆 | C119: 500 | Y119: 62 | Z119: 7.6 | AA119: =Y119*Z119 -> 471.2 | AB119: 73 | AC119: 5.5 | AD119: =AB119*AC119 -> 401.5
C121: =SUM(C100:C120) -> 11244.5 | D121: =SUM(D100:D120) -> 0 | F121: =SUM(F100:F120) -> 0 | G121: =SUM(G100:G120) -> 100 | I121: =SUM(I100:I120) -> 90 | J121: =SUM(J100:J120) -> 161 | L121: =SUM(L100:L120) -> 2657 | M121: =SUM(M100:M120) -> 0 | O121: =SUM(O100:O120) -> 0 | P121: =SUM(P100:P120) -> 0 | R121: =SUM(R100:R120) -> 0 | S121: =SUM(S100:S120) -> 0 | U121: =SUM(U100:U120) -> 0 | V121: =SUM(V100:V120) -> 13.4 | X121: =SUM(X100:X120) -> 335 | Y121: =SUM(Y100:Y120) -> 1057.7 | AA121: =SUM(AA100:AA120) -> 8038.52 | AB121: =SUM(AB100:AB120) -> 897.8 | AD121: =SUM(AD100:AD120) -> 4937.9 | AE121: =SUM(AE100:AE120) -> 662.2 | AG121: =SUM(AG100:AG120) -> 2170.76 | AH121: =SUM(AH100:AH120) -> 0 | AJ121: =SUM(AJ100:AJ120) -> 0 | AK121: =SUM(AK100:AK120) -> 448 | AM121: =SUM(AM100:AM120) -> 2912 | AN121: =SUM(AN100:AN120) -> 925.4 | AP121: =SUM(AP100:AP120) -> 5922.56
A123: 25年8月贾材料明细表 | G123: 李总材料金额合计 | L123: =F138+I138+L138+O138+R138+U138+X138+AA138+AD138+AG138+AJ138+AM138+AP138 -> 17676.55
A124: 日期 | B124: 摘要 | D124: 996钛白粉 | G124: 3000目 | J124: 106D、100C是红色字体 | M124: 7025浆：银粉 | P124: 20000分散 | S124: 8333:红色字体是已稀的 | V124: 4010助 | Y124: 808 | AB124: 807+ | AE124: 812+ | AH124: 811 | AK124: 802A | AN124: 807A
B125: 品名 | C125: 生产量/KG | D125: 数量 | E125: 单价 | F125: 金额 | G125: 数量 | H125: 单价 | I125: 金额 | J125: 数量 | K125: 单价 | L125: 金额 | M125: 数量 | N125: 单价 | O125: 金额 | P125: 数量 | Q125: 单价 | R125: 金额 | S125: 数量 | T125: 单价 | U125: 金额 | V125: 数量 | W125: 单价 | X125: 金额 | Y125: 数量 | Z125: 单价 | AA125: 金额 | AB125: 数量 | AC125: 单价 | AD125: 金额 | AE125: 数量 | AF125: 单价 | AG125: 金额 | AH125: 数量 | AI125: 单价 | AJ125: 金额 | AK125: 数量 | AL125: 单价 | AM125: 金额 | AN125: 数量 | AO125: 单价 | AP125: 金额
A126: 45876 | B126: 优特黑101A-1 | C126: 1000 | Y126: 102 | Z126: 7.9 | AA126: =Y126*Z126 -> 805.8 | AN126: 150 | AO126: 6.3 | AP126: =AN126*AO126 -> 945
A127: 45876 | B127: 中黄浆、购106D:2包*10KG | C127: 225 | J127: 20 | K127: 17 | L127: =J127*K127 -> 340 | Y127: 25 | Z127: 7.9 | AA127: =Y127*Z127 -> 197.5 | AN127: 25 | AO127: 6.3 | AP127: =AN127*AO127 -> 157.5
...

Sheet 回款
A1: 2026年1月贾总回款
A2: 日 期 | B2: 应付款合计金额/元 | E2: 已付款合计金额/元 | F2: 下欠款合计金额/元 | G2: 备 注
B3: =SUM(D7:D34) -> 39250.8 | E3: =SUM(E7:E34) -> 84745 | F3: =B3-E3 -> -45494.2
B5: 明细如下：
B6: 随机单号 | C6: 内容摘要 | D6: 金额 | E6: 已付款金额 | F6: 下欠款金额结存
A7: 11月 | C7: 结存 | E7: 57378 | F7: =D7-E7 -> -57378
A8: 46024 | B8: 2 | C8: 亮光固化剂、包装 | D8: 1885 | F8: =F7+D8-E8 -> -55493
A9: 46025 | B9: 8 | C9: 优特黑101A | D9: 2561.4 | F9: =F8+D9-E9 -> -52931.6
A10: 46031 | C10: 购996钛白粉:14200 | D10: 14200 | F10: =F9+D10-E10 -> -38731.6
A11: 46032 | B11: 22 | C11: 白浆 | D11: 1556 | F11: =F10+D11-E11 -> -37175.6
A12: 46032 | B12: 28 | C12: 桃红 | D12: 250.2 | F12: =F11+D12-E12 -> -36925.4
A13: 46032 | B13: 29 | C13: ABS光油 | D13: 1611.8 | F13: =F12+D13-E13 -> -35313.6
A14: 46036 | C14: 国圣购1/2浆：144KG*16.8=756 | E14: 2419 | F14: =F13+D14-E14 -> -37732.6
A15: 46035 | B15: 36 | C15: 亮白 | D15: 2296 | F15: =F14+D15-E15 -> -35436.6
A16: 46038 | B16: 44 | C16: 亮大红 | D16: 1423 | F16: =F15+D16-E16 -> -34013.6
A17: 46038 | C17: 蓉渝达原材料（预支款） | E17: 24948 | F17: =F16+D17-E17 -> -58961.6
A18: 46041 | B18: 50 | C18: 730#浆 | D18: 6178 | F18: =F17+D18-E18 -> -52783.6
A19: 46043 | B19: 58号 | C19: 平光黑 | D19: 3634 | F19: =F18+D19-E19 -> -49149.6
A20: 46044 | B20: 61 | C20: 沈阳平光黑 | D20: 1547.4 | F20: =F19+D20-E20 -> -47602.2
A21: 46044 | B21: 62 | C21: 亮白 | D21: 2108 | F21: =F20+D21-E21 -> -45494.2
F22: =F21+D22-E22 -> -45494.2
F23: =F22+D23-E23 -> -45494.2
F24: =F23+D24-E24 -> -45494.2
F25: =F24+D25-E25 -> -45494.2
F26: =F25+D26-E26 -> -45494.2
F27: =F26+D27-E27 -> -45494.2
F28: =F27+D28-E28 -> -45494.2
F29: =F28+D29-E29 -> -45494.2
F30: =F29+D30-E30 -> -45494.2
F31: =F30+D31-E31 -> -45494.2
F32: =F31+D32-E32 -> -45494.2
F33: =F32+D33-E33 -> -45494.2
A35: 贾总购钛白粉明细如下：
A36: 日 期 | C36: 内容摘要 | D36: 件数/包 | E36: 数量/KG（规格：25KG/件） | F36: 备注
A37: 2025.12.31 | C37: 贾总结存钛白粉 | E37: 50
A38: 2026.01.09 | C38: 购996钛白粉1吨:14200(未付款） | E38: 1000
A39: 2026.01.10 | C39: 磨白浆1.5槽用钛白粉 | E39: -200
A44: 截止2025年12月30日贾总结存钛白粉数量/KG | E44: =SUM(E37:E43) -> 850
A46: 2025年12月贾总回款
A47: 日 期 | B47: 应付款合计金额/元 | E47: 已付款合计金额/元 | F47: 下欠款合计金额/元 | G47: 备 注
B48: =SUM(D52:D77) -> 47636.6 | E48: =SUM(E52:E77) -> 105015 | F48: =B48-E48 -> -57378.4
B50: 明细如下：
B51: 随机单号 | C51: 内容摘要 | D51: 金额 | E51: 已付款金额 | F51: 下欠款金额结存
A52: 11月 | C52: 结存 | D52: 2439 | F52: =D52-E52 -> 2439
A53: 45993 | B53: 5号 | C53: 电镀大红 | D53: 636 | F53: =F52+D53-E53 -> 3075
A54: 45997 | B54: 13 | C54: 优特黑101A | D54: 2895 | F54: =F53+D54-E54 -> 5970
A55: 45997 | B55: 14 | C55: 全哑白面、黑面、红色和黄色面漆 | D55: 1685 | F55: =F54+D55-E55 -> 7655
A56: 45999 | C56: 蓉渝达原材料（预支款） | E56: 12520 | F56: =F55+D56-E56 -> -4865
A57: 46000 | B57: 21 | C57: 中黄浆 | D57: 1460 | F57: =F56+D57-E57 -> -3405
A58: 46000 | B58: 22 | C58: 亮黄 | D58: 1057.4 | F58: =F57+D58-E58 -> -2347.6
A59: 46001 | B59: 25 | C59: C311黑色浆 | D59: 10550 | F59: =F58+D59-E59 -> 8202.4
A60: 46002 | B60: 30 | C60: 优特黑101A、购乙烷 | D60: 2905 | F60: =F59+D60-E60 -> 11107.4
A61: 46007 | B61: 40 | C61: 亮红、发货包装桶 | D61: 1808 | F61: =F60+D61-E61 -> 12915.4
A62: 46007 | C62: 甲苯胺紫红色粉托运费 | D62: 6 | F62: =F61+D62-E62 -> 12921.4
A63: 46008 | C63: 蓉渝达原材料（预支款） | E63: 9486 | F63: =F62+D63-E63 -> 3435.4
A64: 46011 | C64: 辉杰鞋厂对公国圣 | E64: 60000 | F64: =F63+D64-E64 -> -56564.6
A65: 46011 | C65: 辉杰鞋厂对公国圣税点3% | D65: 1800 | F65: =F64+D65-E65 -> -54764.6
A66: 46014 | B66: 58号 | C66: 柠檬黄、17-19号购发货包装桶 | D66: 1356 | F66: =F65+D66-E66 -> -53408.6
A67: 46014 | B67: 60 | C67: 甲苯胺紫红浆 | D67: 1435 | F67: =F66+D67-E67 -> -51973.6
A68: 46014 | B68: 61 | C68: 哑红 | D68: 1330 | F68: =F67+D68-E68 -> -50643.6
A69: 46015 | B69: 62 | C69: 730#浆 | D69: 9893 | F69: =F68+D69-E69 -> -40750.6
A70: 46017 | B70: 71 | C70: 玫瑰红漆 | D70: 885 | F70: =F69+D70-E70 -> -39865.6
A71: 46020 | B71: 80 | C71: 酞蓝漆 | D71: 526.2 | F71: =F70+D71-E71 -> -39339.4
A72: 46020 | C72: 蓉渝达原材料（预支款） | E72: 23009 | F72: =F71+D72-E72 -> -62348.4
A73: 46021 | B73: 85 | C73: 白浆 | D73: 1192 | F73: =F72+D73-E73 -> -61156.4
A74: 46022 | B74: 87 | C74: 哑白 | D74: 3144 | F74: =F73+D74-E74 -> -58012.4
A75: 46022 | B75: 88 | C75: 白裂纹 | D75: 634 | F75: =F74+D75-E75 -> -57378.4
F76: =F75+D76-E76 -> -57378.4
A78: 贾总购钛白粉明细如下：
A79: 日 期 | C79: 内容摘要 | D79: 件数/包 | E79: 数量/KG（规格：25KG/件） | F79: 备注
A80: 2025.07.17 | C80: 购996钛白粉（17/7开单）:14200 | E80: 1000 | F80: 19/7货单已交贾总
A81: 2025.07.22 | C81: 磨白浆1槽用钛白粉（不加助剂） | E81: -150
A82: 2025.9.22 | C82: 磨白浆1槽用钛白粉（不加助剂） | E82: -150
A83: 2025.10.09 | C83: 磨白浆1槽用钛白粉（不加助剂） | E83: -150
A84: 2025.10.27 | C84: 磨白浆1槽用钛白粉（不加助剂） | E84: -150
A85: 2025.11.15 | C85: 磨白浆1槽用钛白粉（不加助剂） | E85: -200
A86: 2025.12.30 | C86: 磨白浆1槽用钛白粉（不加助剂） | E86: -150
A87: 截止2025年12月30日贾总结存钛白粉数量/KG | E87: =SUM(E80:E86) -> 50
A89: 2025年11月贾总回款
A90: 日 期 | B90: 应付款合计金额/元 | E90: 已付款合计金额/元 | F90: 下欠款合计金额/元 | G90: 备 注
B91: =SUM(D95:D121) -> 75842.7 | E91: =SUM(E95:E121) -> 73404 | F91: =B91-E91 -> 2438.7
B93: 明细如下：
B94: 随机单号 | C94: 内容摘要 | D94: 金额 | E94: 已付款金额 | F94: 下欠款金额结存
A95: 10月 | C95: 结存 | E95: 11370 | F95: =D95-E95 -> -11370
A96: 45962 | B96: 2 | C96: 亮大红 | D96: 1788 | F96: =F95+D96-E96 -> -9582
A97: 45962 | B97: 3 | C97: 亮黄 | D97: 1197.2 | F97: =F96+D97-E97 -> -8384.8
A98: 45966 | B98: 12 | C98: 消光剂：20桶、购买黑浆2KG和包装 | D98: 2531.5 | F98: =F97+D98-E98 -> -5853.3
A99: 45968 | B99: 17 | C99: 沈阳平光黑、20L白桶、酞蓝漆 | D99: 1871 | F99: =F98+D99-E99 -> -3982.3
A100: 45969 | B100: 21 | C100: 烤漆金油、固化剂、包装、双组份亮黑、蓝、哑白 | D100: 4763 | F100: =F99+D100-E100 -> 780.7
A101: 45969 | B101: 22 | C101: 哑红 | D101: 1634 | F101: =F100+D101-E101 -> 2414.7
A102: 45971 | C102: 蓉渝达原材料（预支款） | E102: 23729 | F102: =F101+D102-E102 -> -21314.3
A103: 45975 | B103: 35 | C103: 平光黑 | D103: 3918 | F103: =F102+D103-E103 -> -17396.3
A104: 45975 | B104: 36 | C104: C311黑色浆 | D104: 10593 | F104: =F103+D104-E104 -> -6803.3
A105: 45975 | B105: 40 | C105: 优特黑101A-1、购买样罐 | D105: 2167 | F105: =F104+D105-E105 -> -4636.3
A106: 45976 | B106: 43 | C106: 白浆 | D106: 1580 | F106: =F105+D106-E106 -> -3056.3
A107: 45976 | B107: 44 | C107: 优特黑101A | D107: 2921 | F107: =F106+D107-E107 -> -135.3
A108: 45979 | B108: 49 | C108: 亮白 | D108: 3429 | F108: =F107+D108-E108 -> 3293.7
A109: 45979 | B109: 50 | C109: 哑白 | D109: 2877 | F109: =F108+D109-E109 -> 6170.7
A110: 45981 | B110: 56 | C110: 优特黑101A、双组份亮黄、亮大红 | D110: 2981 | F110: =F109+D110-E110 -> 9151.7
A111: 45982 | B111: 60 | C111: 优特黑101A-1 | D111: 2690 | F111: =F110+D111-E111 -> 11841.7
...

Sheet 代号明细
A1: 贾总2024.12.25
A2: 产品代号 | B2: 名称 | C2: 规格/KG | E2: 产品代号 | F2: 名称 | G2: 规格
A3: 101A | B3: 优特黑 | C3: 17 | E3: 115 | F3: 橙 红 | G3: 17
A4: 101 | B4: 烤漆黑 | C4: 17 | E4: 116 | F4: 桃 红 | G4: 17
A5: 102 | B5: 平光黑 | C5: 17 | E5: 117 | F5: 艳 红 | G5: 17
A6: 103 | B6: 亮 白 | C6: 18 | E6: 118 | F6: 玫瑰红 | G6: 17
A7: 104 | B7: 哑 白 | C7: 18 | E7: 119 | F7: 白裂纹 | G7: 17
A8: 105 | B8: 亮大红 | C8: 17 | E8: 120 | F8: 黑裂纹 | G8: 17
A9: 106 | B9: 哑大红 | C9: 18 | E9: 121 | F9: 弹性漆 | G9: 17
A10: 107 | B10: 亮 黄 | C10: 18 | E10: 122 | F10: 电镀亮白 | G10: 17
A11: 108 | B11: 哑 黄 | C11: 18 | E11: 123 | F11: 电镀中黄 | G11: 18
A12: 109 | B12: 印花精油 | E12: 124 | F12: 电镀大红 | G12: 17
A13: 110 | B13: ABS光油 | C13: 17 | E13: 125 | F13: 电镀黑亮光 | G13: 17
A14: 111 | B14: 酞蓝漆 | C14: 17 | E14: 126 | F14: 电镀黑半光 | G14: 17
A15: 112 | B15: 柠檬黄 | C15: 18 | E15: 127 | F15: 橡皮漆底黑 | G15: 17
A16: 113 | B16: 绿 色 | E16: 128 | F16: 烤漆亮光精油 | G16: 18
A17: 114 | B17: 消光剂 | C17: 16 | E17: 129 | F17: 橡皮漆黑亮光 | G17: 17
E18: 130 | F18: 环保亮黄 | G18: 18
E19: 131 | F19: 环保哑黄 | G19: 18
A21: 11月11日前购的11桶中3#是25%
A22: 11月11 | B22: 购1#浆35% | C22: 200*6*16.5=19800
A23: 11月11 | B23: 购3#浆20% | C23: 190*5桶*13.2=12540

Sheet 24材料明细
A1: 24年12月贾2材料明细表 | T1: 715、730浆含贾总自提的2桶和以前自提均未减账 | AL1: 李总材料金额合计 | AQ1: =AK46+AN46+AQ46+AT46+AW46+AZ46+BC46+BF46+BI46+BL46+BO46+BR46+BU46 -> 36675.878
A2: 日期 | B2: 摘要 | D2: 艳红浆 | E2: 聚酮液 | F2: 甲胺紫浆 | G2: 1206树脂 | H2: 108树脂未统计购货 | I2: 白浆 | J2: 5R大红浆 | K2: 31/8:5R大红浆 | L2: 酞青蓝浆 | M2: 柠檬黄浆 | N2: 橙红浆 | O2: 中黄浆 | P2: C311黑浆 | Q2: 平光黑浆半成品 | R2: 平光黑浆成品 | S2: 7900-2x防尘浆 | T2: 715浆 | U2: 730浆 | V2: 桃红浆 | W2: 5014 | X2: 5050分散剂 | Y2: 120浆 | Z2: 中黄色粉 | AA2: 715粉 | AB2: 730粉 | AC2: 350粉 | AD2: 520粉 | AE2: 橙黄粉 | AF2: C311粉 | AG2: 5RK粉 | AH2: 日期 | AI2: 996钛白粉 | AL2: 3000目 | AO2: 106D、100C是红色字体 | AR2: 7025浆：银粉 | AU2: 20000分散 | AX2: 6920浆 | BA2: 4010助 | BD2: 808 | BG2: 807+ | BJ2: 812+ | BM2: 811 | BP2: 802A | BS2: 807A
B3: 品名 | C3: 生产量/KG | AI3: 数量 | AJ3: 单价 | AK3: 金额 | AL3: 数量 | AM3: 单价 | AN3: 金额 | AO3: 数量 | AP3: 单价 | AQ3: 金额 | AR3: 数量 | AS3: 单价 | AT3: 金额 | AU3: 数量 | AV3: 单价 | AW3: 金额 | AX3: 数量 | AY3: 单价 | AZ3: 金额 | BA3: 数量 | BB3: 单价 | BC3: 金额 | BD3: 数量 | BE3: 单价 | BF3: 金额 | BG3: 数量 | BH3: 单价 | BI3: 金额 | BJ3: 数量 | BK3: 单价 | BL3: 金额 | BM3: 数量 | BN3: 单价 | BO3: 金额 | BP3: 数量 | BQ3: 单价 | BR3: 金额 | BS3: 数量 | BT3: 单价 | BU3: 金额
A4: 11月30 | B4: 30/11结存 | D4: =D54 -> 0 | E4: =E79 -> 587 | F4: =F79 -> 175 | G4: =G79 -> 0 | H4: =H79 -> 0 | I4: =I79 -> 480 | J4: =J79 -> 536 | K4: =K79 -> 0 | L4: =L79 -> -15 | ... AG4: =AG79 -> 0
A5: 12月5 | B5: 亮大红（108：75KG、3号浆107未入库） | C5: 500 | E5: -75 | J5: -75 | AH5: 45631 | BD5: 50 | BE5: 10.5 | BF5: =BD5*BE5 -> 525 | BG5: 118 | BH5: 5.9 | BI5: =BG5*BH5 -> 696.2
A6: 45631 | B6: 桃红漆（桃红浆100KG，树脂75,1号浆52、3号浆73未入库） | C6: 500 | E6: -63 | AH6: 45631 | BD6: 62 | BE6: 10.5 | BF6: =BD6*BE6 -> 651 | BG6: 75 | BH6: 5.9 | BI6: =BG6*BH6 -> 442.5
A7: 45632 | B7: 电镀黑亮光（1206:100、108:12、1号浆21、3号浆：58未入库） | C7: 400 | P7: -60 | AH7: 45632 | BD7: 80 | BE7: 10.5 | BF7: =BD7*BE7 -> 840 | BG7: 69 | BH7: 5.9 | BI7: =BG7*BH7 -> 407.1
A8: 45635 | B8: 烤漆黑（树脂200、1号浆：51、3号浆：214未入库） | C8: 1000 | P8: -150 | AH8: 45635 | BD8: 200 | BE8: 10.5 | BF8: =BD8*BE8 -> 2100 | BG8: 60 | BH8: 5.9 | BI8: =BG8*BH8 -> 354 | BP8: 125 | BQ8: 7.2 | BR8: =BP8*BQ8 -> 900
A9: 45635 | B9: 优特黑（108树脂150、1号浆147、3号浆253未入库） | C9: 1000 | P9: -150 | AH9: 45635 | BD9: 50 | BE9: 10.5 | BF9: =BD9*BE9 -> 525 | BG9: 96 | BH9: 5.9 | BI9: =BG9*BH9 -> 566.4 | BP9: 154 | BQ9: 7.2 | BR9: =BP9*BQ9 -> 1108.8
A10: 45636 | B10: 橡皮漆底黑（二元氯醋：100未入库） | C10: 480 | P10: -84 | AH10: 45636 | AO10: 22 | AP10: 17 | AQ10: =AO10*AP10 -> 374 | BD10: 80 | BE10: 10.5 | BF10: =BD10*BE10 -> 840 | BG10: 94 | BH10: 5.9 | BI10: =BG10*BH10 -> 554.6 | BJ10: 60 | BK10: 3.6 | BL10: =BJ10*BK10 -> 216 | BP10: 40 | BQ10: 6.8 | BR10: =BP10*BQ10 -> 272
A11: 45638 | B11: 中黄浆（中黄粉：25KG,108:10未入库 | C11: 45 | AH11: 45638 | BD11: 5 | BE11: 9.3 | BF11: =BD11*BE11 -> 46.5 | BS11: 5 | BT11: 7.8 | BU11: =BS11*BT11 -> 39
A12: 45638 | B12: 入库中黄浆：15%的损耗 | O12: 38 | AH12: 45638
A13: 45639 | B13: 优特黑（108树脂150、1号浆147、3号浆253未入库） | C13: 1000 | P13: -150 | AH13: 45635 | BD13: 50 | BE13: 9.3 | BF13: =BD13*BE13 -> 465 | BG13: 95 | BH13: 5.9 | BI13: =BG13*BH13 -> 560.5 | BP13: 155 | BQ13: 6.8 | BR13: =BP13*BQ13 -> 1054
A14: 45640 | B14: 白浆（树脂：96KG,5014B:9KG未入库） | C14: 525 | AH14: 45640 | AI14: 300 | BP14: 60 | BQ14: 6.8 | BR14: =BP14*BQ14 -> 408 | BS14: 60 | BT14: 7.8 | BU14: =BS14*BT14 -> 468
A15: 45640 | B15: 入库白浆（2%损耗） | I15: 514 | AH15: 45640
A16: 45640 | B16: 柠檬黄漆（108树脂：58、柠檬浆63、1#浆26、3#浆：37未入库 | C16: 252 | AH16: 45640 | BD16: 30 | BE16: 9.3 | BF16: =BD16*BE16 -> 279 | BG16: 38 | BH16: 5.9 | BI16: =BG16*BH16 -> 224.2
A17: 45643 | B17: 亮白普（108：200KG、外购715:51KG、外购730:214KG未入库） | C17: 1000 | E17: -125 | I17: -200 | AH17: 45643 | BD17: 25 | BE17: 9.3 | BF17: =BD17*BE17 -> 232.5 | BG17: 135 | BH17: 5.9 | BI17: =BG17*BH17 -> 796.5 | BP17: 50 | BQ17: 6.8 | BR17: =BP17*BQ17 -> 340
A18: 45644 | B18: 玫瑰红漆（树脂45KG、3号浆64未入库） | C18: 300 | E18: -45 | F18: -45 | AH18: 45644 | BD18: 30 | BE18: 9.3 | BF18: =BD18*BE18 -> 279 | BG18: 61 | BH18: 5.9 | BI18: =BG18*BH18 -> 359.9 | BP18: 10 | BQ18: 6.8 | BR18: =BP18*BQ18 -> 68
A19: 45644 | B19: 哑白普(108:100，色片白100、白浆100、715浆136、防尘浆2.5） | C19: 1052.5 | Y19: -260 | AH19: 45644 | AL19: 50 | AM19: 0.9 | AN19: =AL19*AM19 -> 45 | AO19: 25 | AP19: 17 | AQ19: =AO19*AP19 -> 425 | BJ19: 279 | BK19: 3.6 | BL19: =BJ19*BK19 -> 1004.4
A20: 45644 | B20: 亮黄漆（108:6.48,1#浆：10.08,3#浆：2.52，黄浆：7.2 | C20: 36 | E20: -3.6 | AH20: 45644 | BD20: 1.8 | BE20: 9.3 | BF20: =BD20*BE20 -> 16.74 | BG20: 4.32 | BH20: 5.9 | BI20: =BG20*BH20 -> 25.488
A21: 45646 | B21: ABS光油（108:150,1/4浆（715）：85 730浆：160 | C21: 500 | AH21: 45646 | BD21: 105 | BE21: 9.3 | BF21: =BD21*BE21 -> 976.5
A22: 45646 | B22: 哑红（树脂：50KG，1/4）：70,，防尘浆：2，改亮大红：53未入库） | C22: 606 | J22: -75 | Y22: -130 | AH22: 45646 | AL22: 50 | AM22: 0.9 | AN22: =AL22*AM22 -> 45 | AO22: 16 | AP22: 17 | AQ22: =AO22*AP22 -> 272 | BG22: 30 | BH22: 5.9 | BI22: =BG22*BH22 -> 177 | BJ22: 130 | BK22: 3.6 | BL22: =BJ22*BK22 -> 468
A23: 12月20-21 | B23: C311黑浆（色粉：100KG,树脂200KG未计入库存） | C23: 750 | AH23: 12-20-21 | AU23: 25 | AV23: 75 | AW23: =AU23*AV23 -> 1875 | BD23: 300 | BE23: 9.3 | BF23: =BD23*BE23 -> 2790 | BG23: 125 | BH23: 5.9 | BI23: =BG23*BH23 -> 737.5
A24: 45647 | B24: 入库黑色浆 | P24: 735 | AH24: 45647
A25: 45647 | B25: 亮白普（108180KG、外购715:46KG、外购730:193KG未入库） | C25: 900 | E25: -112 | I25: -180 | AH25: 45647 | BD25: 23 | BE25: 9.3 | BF25: =BD25*BE25 -> 213.9 | BG25: 121 | BH25: 5.9 | BI25: =BG25*BH25 -> 713.9 | BP25: 45 | BQ25: 6.8 | BR25: =BP25*BQ25 -> 306
A26: 45647 | B26: 烤漆黑（树脂200、1号浆：51、3号浆：214未入库） | C26: 1000 | P26: -150 | AH26: 45647 | BD26: 200 | BE26: 9.3 | BF26: =BD26*BE26 -> 1860 | BG26: 60 | BH26: 5.9 | BI26: =BG26*BH26 -> 354 | BP26: 125 | BQ26: 6.8 | BR26: =BP26*BQ26 -> 850
A27: 45649 | B27: 亮黄（树脂27，1号浆：,421、3号浆：10.5未入库 | C27: 150 | E27: -15 | N27: -30 | AH27: 45649 | BD27: 7.5 | BE27: 9.3 | BF27: =BD27*BE27 -> 69.75 | BG27: 18 | BH27: 5.9 | BI27: =BG27*BH27 -> 106.2
A28: 45650 | B28: 亮大红（108：90KG、3号浆128未入库） | C28: 600 | E28: -90 | J28: -90 | AH28: 45650 | BD28: 60 | BE28: 9.3 | BF28: =BD28*BE28 -> 558 | BG28: 142 | BH28: 5.9 | BI28: =BG28*BH28 -> 837.8
A29: 45650 | B29: 平光黑（树脂150、3#浆145、6920；3未入库） | C29: 1003 | P29: -120 | T29: -140 | AH29: 45650 | AO29: 30 | AP29: 17 | AQ29: =AO29*AP29 -> 510 | BD29: 100 | BE29: 9.3 | BF29: =BD29*BE29 -> 930 | BG29: 40 | BH29: 5.9 | BI29: =BG29*BH29 -> 236 | BJ29: 200 | BK29: 3.6 | BL29: =BJ29*BK29 -> 720 | BP29: 75 | BQ29: 6.8 | BR29: =BP29*BQ29 -> 510
A30: 45651 | B30: 消光剂（树脂：3） | C30: 160 | AH30: 45651 | AO30: 20 | AP30: 15 | AQ30: =AO30*AP30 -> 300 | BG30: 64 | BH30: 5.9 | BI30: =BG30*BH30 -> 377.6 | BP30: 73 | BQ30: 6.8 | BR30: =BP30*BQ30 -> 496.4
A31: 45657 | B31: 白浆（树脂：96KG,5014B:9KG未入库） | C31: 525 | AH31: 45657 | AI31: 300 | BP31: 60 | BQ31: 6.8 | BR31: =BP31*BQ31 -> 408 | BS31: 60 | BT31: 7.8 | BU31: =BS31*BT31 -> 468
A32: 45657 | B32: 入库白浆（2%损耗） | I32: 514 | AH32: 45657
C46: =SUM(C5:C45) -> 14284.5 | D46: =SUM(D5:D26) -> 0 | E46: =SUM(E4:E45) -> 58.4 | F46: =SUM(F4:F45) -> 130 | G46: =SUM(G4:G45) -> 0 | H46: =SUM(H4:H45) -> 0 | I46: =SUM(I4:I45) -> 1128 | J46: =SUM(J4:J45) -> 296 | K46: =SUM(K4:K45) -> 0 | L46: =SUM(L4:L45) -> -15 | ... AG46: =SUM(AG4:AG45) -> 0 | AI46: =SUM(AI4:AI45) -> 600 | AK46: =SUM(AK4:AK45) -> 0 | AL46: =SUM(AL4:AL45) -> 100 | AN46: =SUM(AN4:AN45) -> 90 | AO46: =SUM(AO4:AO45) -> 113 | AQ46: =SUM(AQ4:AQ45) -> 1881 | AR46: =SUM(AR4:AR45) -> 0 | AT46: =SUM(AT4:AT45) -> 0 | AU46: =SUM(AU4:AU45) -> 25 | AW46: =SUM(AW4:AW45) -> 1875 | AX46: =SUM(AX4:AX45) -> 0 | AZ46: =SUM(AZ4:AZ45) -> 0 | BA46: =SUM(BA4:BA45) -> 0 | BC46: =SUM(BC4:BC45) -> 0 | BD46: =SUM(BD4:BD45) -> 1459.3 | BF46: =SUM(BF4:BF45) -> 14197.89 | BG46: =SUM(BG4:BG45) -> 1445.32 | BI46: =SUM(BI4:BI45) -> 8527.388 | BJ46: =SUM(BJ4:BJ45) -> 669 | BL46: =SUM(BL4:BL45) -> 2408.4 | BM46: =SUM(BM4:BM45) -> 0 | BO46: 0 | BP46: =SUM(BP4:BP45) -> 972 | BR46: =SUM(BR4:BR45) -> 6721.2 | BS46: =SUM(BS4:BS45) -> 125 | BU46: =SUM(BU4:BU45) -> 975
A51: 24年10月贾总材料明细表 | T51: 715、730浆含贾总自提的2桶和以前自提均未减账 | AL51: 李总材料金额合计 | AQ51: =AK79+AN79+AQ79+AT79+AW79+AZ79+BC79+BF79+BI79+BL79+BO79+BR79+BU79 -> 33968.92
A52: 日期 | B52: 摘要 | D52: 艳红浆 | E52: 聚酮液 | F52: 甲胺紫浆 | G52: 1206树脂 | H52: 108树脂未统计购货 | I52: 白浆 | J52: 5R大红浆 | K52: 31/8:5R大红浆 | L52: 酞青蓝浆 | M52: 柠檬黄浆 | N52: 橙红浆 | O52: 中黄浆 | P52: C311黑浆 | Q52: 平光黑浆半成品 | R52: 平光黑浆成品 | S52: 7900-2x防尘浆 | T52: 715浆 | U52: 730浆 | V52: 桃红浆 | W52: 5014 | X52: 5050分散剂 | Y52: 120浆 | Z52: 中黄色粉 | AA52: 715粉 | AB52: 730粉 | AC52: 350粉 | AD52: 520粉 | AE52: 橙黄粉 | AF52: C311粉 | AG52: 5RK粉 | AH52: 日期 | AI52: 996钛白粉 | AL52: 3000目 | AO52: 106D、100C是红色字体 | AR52: 7025浆：银粉 | AU52: 20000分散 | AX52: 6920浆 | BA52: 4010助 | BD52: 808 | BG52: 807+ | BJ52: 812+ | BM52: 811 | BP52: 802A | BS52: 807A
B53: 品名 | C53: 生产量/KG | AI53: 数量 | AJ53: 单价 | AK53: 金额 | AL53: 数量 | AM53: 单价 | AN53: 金额 | AO53: 数量 | AP53: 单价 | AQ53: 金额 | AR53: 数量 | AS53: 单价 | AT53: 金额 | AU53: 数量 | AV53: 单价 | AW53: 金额 | AX53: 数量 | AY53: 单价 | AZ53: 金额 | BA53: 数量 | BB53: 单价 | BC53: 金额 | BD53: 数量 | BE53: 单价 | BF53: 金额 | BG53: 数量 | BH53: 单价 | BI53: 金额 | BJ53: 数量 | BK53: 单价 | BL53: 金额 | BM53: 数量 | BN53: 单价 | BO53: 金额 | BP53: 数量 | BQ53: 单价 | BR53: 金额 | BS53: 数量 | BT53: 单价 | BU53: 金额
A54: 10月 | B54: 31/10结存 | D54: =D130 -> 0 | E54: =E130 -> 382 | F54: =F130 -> 175 | G54: =G130 -> 0 | H54: =H130 -> 0 | I54: =I130 -> 666 | J54: =J130 -> 611 | K54: =K130 -> 0 | ... AG54: =AG130 -> 0
A55: 45597 | B55: 白浆（树脂：48KG,5014B:4.5KG未入库） | C55: 262.5 | AH55: 45597 | AI55: 150 | BP55: 30 | BQ55: 7.2 | BR55: =BP55*BQ55 -> 216 | BS55: 30 | BT55: 7.5 | BU55: =BS55*BT55 -> 225
A56: 45597 | B56: 入库白浆（2%损耗） | I56: 257 | AH56: 45597
A57: 45603 | B57: 亮白普（108：200KG、外购715:51KG、外购730:214KG未入库） | C57: 1000 | E57: -125 | I57: -200 | AH57: 45603 | BD57: 25 | BE57: 10.6 | BF57: =BD57*BE57 -> 265 | BG57: 78 | BH57: 6.3 | BI57: =BG57*BH57 -> 491.4 | BP57: 107 | BQ57: 7.2 | BR57: =BP57*BQ57 -> 770.4
A58: 45604 | B58: 烤漆黑（树脂200、715外购51、730外购214未入库） | C58: 1000 | P58: -150 | AH58: 45604 | BD58: 200 | BE58: 10.6 | BF58: =BD58*BE58 -> 2120 | BG58: 60 | BH58: 6.3 | BI58: =BG58*BH58 -> 378 | BP58: 125 | BQ58: 7.2 | BR58: =BP58*BQ58 -> 900
A59: 45604 | B59: 哑白普（色片白：100KG,树脂100KG未入库） | C59: 1052.5 | I59: -100 | S59: -2.5 | T59: -136 | Y59: -260 | AH59: 45604 | AL59: 50 | AM59: 0.9 | AN59: =AL59*AM59 -> 45 | AO59: 25 | AP59: 17 | AQ59: =AO59*AP59 -> 425 | BJ59: 279 | BK59: 3.7 | BL59: =BJ59*BK59 -> 1032.3
A60: 45607 | B60: 稀料540 | C60: 540 | AH60: 45607 | BD60: 60 | BE60: 10.6 | BF60: =BD60*BE60 -> 636 | BG60: 120 | BH60: 6.3 | BI60: =BG60*BH60 -> 756 | BJ60: 270 | BK60: 3.7 | BL60: =BJ60*BK60 -> 999 | BP60: 90 | BQ60: 7.2 | BR60: =BP60*BQ60 -> 648
A61: 45608 | B61: 亮黄普（树脂：56、715外购28、、外购112未入库） | C61: 400 | E61: -40 | O61: -60 | AH61: 45610 | BD61: 28 | BE61: 10.6 | BF61: =BD61*BE61 -> 296.8 | BG61: 76 | BH61: 6.3 | BI61: =BG61*BH61 -> 478.8
A62: 45615 | B62: 亮白普（108：200KG、外购715:51KG、外购730:214KG未入库） | C62: 1000 | E62: -125 | I62: -200 | T62: -51 | U62: -214 | AH62: 45615 | BD62: 25 | BE62: 10.6 | BF62: =BD62*BE62 -> 265 | BG62: 78 | BH62: 6.3 | BI62: =BG62*BH62 -> 491.4 | BP62: 107 | BQ62: 7.2 | BR62: =BP62*BQ62 -> 770.4
A63: 45616 | B63: 亮大红（108：75KG、未入库） | C63: 500 | E63: -75 | J63: -75 | U63: -190 | AH63: 45616 | BD63: 50 | BE63: 10.6 | BF63: =BD63*BE63 -> 530 | BG63: 35 | BH63: 6.3 | BI63: =BG63*BH63 -> 220.5
A64: 45616 | B64: 烤漆黑（树脂400未入库） | C64: 2000 | P64: -300 | T64: -140 | U64: -760 | AH64: 45616 | BD64: 400 | BE64: 10.6 | BF64: =BD64*BE64 -> 4240 | BI64: =BG64*BH64 -> 0
A65: 45616 | B65: 聚酮液（19/9入库聚酮粉：1000KG-300:21/9-300：20/11) | C65: 750 | AH65: 45616 | BD65: 450 | BE65: 10.6 | BF65: =BD65*BE65 -> 4770
A66: 45616 | B66: 入库：聚酮液（2%损耗已减） | E66: 735 | AH66: 45616
A67: 45616 | B67: 平光黑（树脂150未入库） | C67: 1003 | P67: -120 | S67: -3 | T67: -140 | U67: -260 | AH67: 45616 | AO67: 30 | AP67: 17 | AQ67: =AO67*AP67 -> 510 | BD67: 100 | BE67: 10.5 | BF67: =BD67*BE67 -> 1050 | BJ67: 200 | BK67: 3.7 | BL67: =BJ67*BK67 -> 740
A68: 45617 | B68: 亮黄普（树脂：56、715外购28、、外购50未入库） | C68: 400 | E68: -40 | O68: -60 | U68: -110 | AH68: 45617 | BD68: 28 | BE68: 10.5 | BF68: =BD68*BE68 -> 294 | BG68: 28 | BH68: 6.3 | BI68: =BG68*BH68 -> 176.4
A69: 45617 | B69: 消光剂（树脂：0.4） | C69: 16.9 | AH69: 45617 | AO69: 2 | AP69: 15 | AQ69: =AO69*AP69 -> 30 | BG69: 6.4 | BH69: 6.4 | BI69: =BG69*BH69 -> 40.96 | BP69: 8.1 | BQ69: 8.6 | BR69: =BP69*BQ69 -> 69.66
A70: 45619 | B70: 白浆（树脂：48KG,5014B:4.5KG未入库） | C70: 262.5 | AH70: 45619 | AI70: 150 | BP70: 30 | BQ70: 7.2 | BR70: =BP70*BQ70 -> 216 | BS70: 30 | BT70: 7.8 | BU70: =BS70*BT70 -> 234
A71: 45619 | B71: 入库白浆（2%损耗） | I71: 257 | AH71: 45619
A72: 11-25、26 | B72: C311黑浆（色粉：100KG,树脂200KG未计入库存） | C72: 750 | AH72: 11-25、26 | AU72: 25 | AV72: 75 | AW72: =AU72*AV72 -> 1875 | BD72: 300 | BE72: 10.5 | BF72: =BD72*BE72 -> 3150 | BG72: 125 | BH72: 6.3 | BI72: =BG72*BH72 -> 787.5
A73: 45625 | B73: 亮白普（108：200KG、外购715:51KG、外购730:214KG未入库） | C73: 1000 | E73: -125 | I73: -200 | S73: -2.5 | AH73: 45625 | BD73: 25 | BE73: 10.5 | BF73: =BD73*BE73 -> 262.5 | BG73: 135 | BH73: 5.9 | BI73: =BG73*BH73 -> 796.5 | BP73: 50 | BQ73: 7.2 | BR73: =BP73*BQ73 -> 360
A74: 45625 | B74: 亮黄改遮盖力54未入库 | C74: 57 | O74: -3
A75: 45625 | B75: 亮白改哑白（半成品540、色片白100未入库） | C75: 1130 | T75: -101 | Y75: -70 | AH75: 45625 | AL75: 50 | AM75: 0.9 | AN75: =AL75*AM75 -> 45 | AO75: 30 | AP75: 17 | AQ75: =AO75*AP75 -> 510 | BJ75: 236.5 | BK75: 3.6 | BL75: =BJ75*BK75 -> 851.4
C79: =SUM(C54:C78) -> 13124.4 | D79: =SUM(D54:D78) -> 0 | E79: =SUM(E54:E78) -> 587 | F79: =SUM(F54:F78) -> 175 | G79: =SUM(G54:G78) -> 0 | H79: =SUM(H54:H78) -> 0 | I79: =SUM(I54:I78) -> 480 | J79: =SUM(J54:J78) -> 536 | ... AG79: =SUM(AG54:AG78) -> 0 | AI79: =SUM(AI54:AI78) -> 300 | AJ79: =SUM(AJ54:AJ76) -> 0 | AK79: =SUM(AK54:AK76) -> 0 | AL79: =SUM(AL54:AL78) -> 100 | AN79: =SUM(AN54:AN78) -> 90 | AO79: =SUM(AO54:AO78) -> 87 | AQ79: =SUM(AQ54:AQ78) -> 1475 | AR79: =SUM(AR54:AR76) -> 0 | AT79: =SUM(AT54:AT76) -> 0 | AU79: =SUM(AU54:AU78) -> 25 | AW79: =SUM(AW54:AW78) -> 1875 | AX79: =SUM(AX54:AX78) -> 0 | AZ79: =SUM(AZ54:AZ78) -> 0 | BA79: =SUM(BA54:BA78) -> 0 | BC79: =SUM(BC54:BC78) -> 0 | BD79: =SUM(BD54:BD78) -> 1691 | BF79: =SUM(BF54:BF78) -> 17879.3 | BG79: =SUM(BG54:BG78) -> 741.4 | BI79: =SUM(BI54:BI78) -> 4617.46 | BJ79: =SUM(BJ54:BJ78) -> 985.5 | BL79: =SUM(BL54:BL78) -> 3622.7 | BM79: =SUM(BM54:BM76) -> 0 | BO79: =SUM(BO54:BO76) -> 0 | BP79: =SUM(BP54:BP78) -> 547.1 | BR79: =SUM(BR54:BR78) -> 3950.46 | BS79: =SUM(BS54:BS78) -> 60 | BU79: =SUM(BU54:BU78) -> 459
A90: 24年10月贾总材料明细表 | T90: 715、730浆含贾总自提的2桶和以前自提均未减账 | AL90: 李总材料金额合计 | AQ90: =AK130+AN130+AQ130+AT130+AW130+AZ130+BC130+BF130+BI130+BL130+BO130+BR130+BU130 -> 67294.7
A91: 日期 | B91: 摘要 | D91: 艳红浆 | E91: 聚酮液 | F91: 甲胺紫浆 | G91: 1206树脂 | H91: 108树脂未统计购货 | I91: 白浆 | J91: 5R大红浆 | K91: 31/8:5R大红浆 | L91: 酞青蓝浆 | M91: 柠檬黄浆 | N91: 橙红浆 | O91: 中黄浆 | P91: C311黑浆 | Q91: 平光黑浆半成品 | R91: 平光黑浆成品 | S91: 7900-2x防尘浆 | T91: 715浆 | U91: 730浆 | V91: 桃红浆 | W91: 5014 | X91: 5050分散剂 | Y91: 120浆 | Z91: 中黄色粉 | AA91: 715粉 | AB91: 730粉 | AC91: 350粉 | AD91: 520粉 | AE91: 橙黄粉 | AF91: C311粉 | AG91: 5RK粉 | AH91: 日期 | AI91: 996钛白粉 | AL91: 3000目 | AO91: 106D | AR91: 7025浆：银粉 | AU91: 20000分散 | AX91: 6920浆 | BA91: 4010助 | BD91: 808 | BG91: 807+ | BJ91: 812+ | BM91: 811 | BP91: 802A | BS91: 807A
B92: 品名 | C92: 生产量/KG | AI92: 数量 | AJ92: 单价 | AK92: 金额 | AL92: 数量 | AM92: 单价 | AN92: 金额 | AO92: 数量 | AP92: 单价 | AQ92: 金额 | AR92: 数量 | AS92: 单价 | AT92: 金额 | AU92: 数量 | AV92: 单价 | AW92: 金额 | AX92: 数量 | AY92: 单价 | AZ92: 金额 | BA92: 数量 | BB92: 单价 | BC92: 金额 | BD92: 数量 | BE92: 单价 | BF92: 金额 | BG92: 数量 | BH92: 单价 | BI92: 金额 | BJ92: 数量 | BK92: 单价 | BL92: 金额 | BM92: 数量 | BN92: 单价 | BO92: 金额 | BP92: 数量 | BQ92: 单价 | BR92: 金额 | BS92: 数量 | BT92: 单价 | BU92: 金额
A93: 9月 | B93: 31/8结存 | D93: =D155 -> 0 | E93: =E155 -> 212 | F93: =F155 -> 175 | G93: =G155 -> 0 | H93: =H155 -> 0 | I93: =I155 -> 566.5 | J93: =J155 -> 727 | K93: =K155 -> 109 | ... X93: =X155 -> 13.5 | Z93: =Z155 -> 0 | AA93: =AA155 -> 0 | AB93: =AB155 -> 0 | AC93: =AC155 -> 14 | AD93: =AD155 -> 0 | AE93: =AE155 -> 0 | AF93: =AF155 -> 0 | AG93: =AG155 -> 0
A94: 45572 | B94: 哑红（树脂：50KG未入库） | C94: 552 | J94: -75 | S94: -2 | T94: -70 | U94: -130 | AH94: 45572 | AL94: 50 | AM94: 0.9 | AN94: =AL94*AM94 -> 45 | AO94: 15 | AP94: 17 | AQ94: =AO94*AP94 -> 255 | BJ94: 160 | BK94: 3.7 | BL94: =BJ94*BK94 -> 592
A95: 45573 | B95: 白浆（树脂：96KG,5014B:9KG未入库） | C95: 525 | AH95: 45573 | AI95: 300 | BP95: 60 | BQ95: 7.8 | BR95: =BP95*BQ95 -> 468 | BS95: 60 | BT95: 7.7 | BU95: =BS95*BT95 -> 462
A96: 45573 | B96: 入库白浆（损耗2%） | I96: 514.5 | AH96: 45573
A97: 45575 | B97: ABS光油(树脂：210未入库， | C97: 700 | T97: -119 | U97: -224 | AH97: 45575 | BD97: 147 | BE97: 10.7 | BF97: =BD97*BE97 -> 1572.9
A98: 45576 | B98: 亮黄普（树脂：70未入库） | C98: 500 | E98: -50 | O98: -75 | T98: -70 | U98: -200 | AH98: 45576 | BD98: 35 | BE98: 10.7 | BF98: =BD98*BE98 -> 374.5
A99: 45576 | B99: 730浆（200KG：730粉未入库） | C99: 1280 | AH99: 45576 | BG99: 720 | BH99: 6.2 | BI99: =BG99*BH99 -> 4464 | BP99: 360 | BQ99: 7.8 | BR99: =BP99*BQ99 -> 2808
A100: 45576 | B100: 入库730浆 | U100: 1280 | AH100: 45576
A101: 45576 | B101: ABS亮大红（树脂：75未入库） | C101: 500 | E101: -75 | K101: -75 | U101: -190 | AH101: 45576 | BD101: 50 | BE101: 10.7 | BF101: =BD101*BE101 -> 535 | BG101: 35 | BH101: 6.2 | BI101: =BG101*BH101 -> 217
A102: 45577 | B102: 将亮黄改成哑黄（自备亮黄：560KG、未入库） | C102: 640.5 | S102: -2.5 | AH102: 45577 | AL102: 56 | AM102: 0.9 | AN102: =AL102*AM102 -> 50.4 | AO102: 17 | AP102: 17 | AQ102: =AO102*AP102 -> 289 | BG102: 2 | BH102: 6.2 | BI102: =BG102*BH102 -> 12.4 | BJ102: 3 | BK102: 3.7 | BL102: =BJ102*BK102 -> 11.1
A103: 45577 | B103: 烤漆黑（树脂400未入库） | C103: 2000 | P103: -300 | T103: -140 | U103: -760 | AH103: 45577 | BD103: 400 | BE103: 10.6 | BF103: =BD103*BE103 -> 4240
A104: 45579 | B104: 平光黑（树脂150未入库） | C104: 1003 | P104: -120 | S104: -3 | T104: -140 | U104: -260 | AH104: 45579 | AO104: 30 | AP104: 17 | AQ104: =AO104*AP104 -> 510 | BD104: 100 | BE104: 10.6 | BF104: =BD104*BE104 -> 1060 | BJ104: 200 | BK104: 3.7 | BL104: =BJ104*BK104 -> 740
A105: 45579 | B105: 改黑裂纹漆(半成品：380KG：350哑粉:60KG） | C105: 815 | R105: -30 | AH105: 45579 | BG105: 165 | BH105: 6.2 | BI105: =BG105*BH105 -> 1023 | BJ105: 180 | BK105: 3.7 | BL105: =BJ105*BK105 -> 666
A106: 45580 | B106: 半哑白（树脂：46KG未入库) | C106: 380 | I106: -80 | S106: -1 | T106: -47 | U106: -90 | AH106: 45580 | AL106: 18 | AM106: 0.9 | AN106: =AL106*AM106 -> 16.2 | AO106: 3 | AP106: 17 | AQ106: =AO106*AP106 -> 51 | BJ106: 95 | BK106: 3.7 | BL106: =BJ106*BK106 -> 351.5
A107: 10月14-15 | B107: C311黑浆（色粉：100=10件*10、树脂200未计入库存） | C107: 750 | AH107: 10月14-15 | AU107: 25 | AV107: 75 | AW107: =AU107*AV107 -> 1875 | BD107: 300 | BE107: 10.6 | BF107: =BD107*BE107 -> 3180 | BG107: 125 | BH107: 6.3 | BI107: =BG107*BH107 -> 787.5
A108: 45580 | B108: 入库C311黑色浆浆(损耗14KG) | P108: 736 | AH108: 45580
A109: 45580 | B109: 莹光浆（莹光粉：10、树脂：10、5014B:0.6未入库） | C109: 61.3 | S109: -0.7 | AH109: 45580 | BD109: 16 | BE109: 10.6 | BF109: =BD109*BE109 -> 169.6 | BG109: 16 | BH109: 6.3 | BI109: =BG109*BH109 -> 100.8
A110: 45582 | B110: 亮白普（树脂128KG未入库） | C110: 640 | E110: -80 | I110: -128 | T110: -45 | U110: -243 | AH110: 45582 | BD110: 16 | BE110: 10.6 | BF110: =BD110*BE110 -> 169.6
A111: 45586 | B111: 聚酮液（19/9入库聚酮粉：1000KG-300:21/9) | C111: 750 | AH111: 45586 | BD111: 450 | BE111: 10.6 | BF111: =BD111*BE111 -> 4770
A112: 45586 | B112: 入库：聚酮液 | E112: 750 | AH112: 45586
A113: 45587 | B113: 平光黑（树脂150未入库） | C113: 1003 | P113: -120 | S113: -3 | T113: -140 | U113: -260 | AH113: 45587 | AO113: 30 | AP113: 17 | AQ113: =AO113*AP113 -> 510 | BD113: 100 | BE113: 10.6 | BF113: =BD113*BE113 -> 1060 | BJ113: 200 | BK113: 3.7 | BL113: =BJ113*BK113 -> 740
A114: 45588 | B114: 730浆（200KG：730粉未入库） | C114: 1280 | AH114: 45588 | BG114: 720 | BH114: 6.3 | BI114: =BG114*BH114 -> 4536 | BP114: 360 | BQ114: 7.2 | BR114: =BP114*BQ114 -> 2592
A115: 45588 | B115: 入库730浆 | U115: 1280 | AH115: 45588
A116: 45589 | B116: 亮白普（白浆：200KG未入库） | C116: 1000 | E116: -125 | I116: -200 | T116: -70 | U116: -380 | AH116: 45589 | BD116: 25 | BE116: 10.6 | BF116: =BD116*BE116 -> 265
A117: 45591 | B117: 715浆（1/4粉：375未入库） | C117: 1275 | AH117: 45591 | BG117: 720 | BH117: 6.3 | BI117: =BG117*BH117 -> 4536 | BP117: 180 | BQ117: 7.2 | BR117: =BP117*BQ117 -> 1296
A118: 45591 | B118: 入库715浆 | T118: 1275 | AH118: 45591
A119: 45594 | B119: 120浆（120粉：150未入库） | C119: 1230 | AH119: 45594 | BG119: 720 | BH119: 6.3 | BI119: =BG119*BH119 -> 4536 | BP119: 360 | BQ119: 7.2 | BR119: =BP119*BQ119 -> 2592
A120: 45594 | B120: 入库120浆 | Y120: 1230 | AH120: 45594
A121: 45594 | B121: 白裂纹（树脂：32KG，350哑粉:40未入库） | C121: 607 | I121: -64 | Y121: -126 | AH121: 45594 | BG121: 128 | BH121: 6.3 | BI121: =BG121*BH121 -> 806.4 | BJ121: 217 | BK121: 3.7 | BL121: =BJ121*BK121 -> 802.9
A122: 45594 | B122: 730浆（150KG：730粉未入库） | C122: 960 | AH122: 45594 | BG122: 540 | BH122: 6.3 | BI122: =BG122*BH122 -> 3402 | BP122: 270 | BQ122: 7.2 | BR122: =BP122*BQ122 -> 1944
A123: 45594 | B123: 入库960浆 | U123: 960 | AH123: 45594
A124: 45595 | B124: 白浆（树脂：48KG,5014B:4.5KG未入库） | C124: 262.5 | AH124: 45595 | AI124: 150 | BP124: 30 | BQ124: 7.2 | BR124: =BP124*BQ124 -> 216 | BS124: 30 | BT124: 7.5 | BU124: =BS124*BT124 -> 225
A125: 45595 | B125: 入库白浆（2%损耗） | I125: 257 | AH125: 45595
A126: 45596 | B126: 酞青蓝漆（树脂75、酞青蓝浆75未入库） | E126: -50 | T126: -70 | U126: -165 | AH126: 45596 | BD126: 80 | BE126: 10.6 | BF126: =BD126*BE126 -> 848
A127: 45596 | B127: ABS亮大红（树脂：75未入库、大红41KG 以前的） | E127: -75 | J127: -41 | K127: -34 | U127: -190 | AH127: 45596 | BD127: 50 | BE127: 10.6 | BF127: =BD127*BE127 -> 530 | BG127: 35 | BH127: 6.3 | BI127: =BG127*BH127 -> 220.5
A128: 45596 | B128: 亮白普（108：200KG未入库） | C128: 1000 | E128: -125 | I128: -200 | T128: -51 | U128: -214 | AH128: 45596 | BD128: 25 | BE128: 10.6 | BF128: =BD128*BE128 -> 265 | BG128: 78 | BH128: 6.3 | BI128: =BG128*BH128 -> 491.4 | BP128: 107 | BQ128: 7.2 | BR128: =BP128*BQ128 -> 770.4
A129: 45596 | B129: 优特黑（树脂150K未入库） | C129: 1000 | P129: -150 | T129: -147 | U129: -253 | AH129: 45596 | BD129: 50 | BE129: 10.6 | BF129: =BD129*BE129 -> 530 | BG129: 96 | BH129: 6.3 | BI129: =BG129*BH129 -> 604.8 | BP129: 154 | BQ129: 7.2 | BR129: =BP129*BQ129 -> 1108.8
C130: =SUM(C93:C129) -> 20714.3 | D130: =SUM(D93:D129) -> 0 | E130: =SUM(E93:E129) -> 382 | F130: =SUM(F93:F129) -> 175 | G130: =SUM(G93:G129) -> 0 | H130: =SUM(H93:H129) -> 0 | I130: =SUM(I93:I129) -> 666 | J130: =SUM(J93:J129) -> 611 | ... AG130: =SUM(AG93:AG129) -> 0 | AI130: =SUM(AI93:AI129) -> 450 | AJ130: =SUM(AJ93:AJ117) -> 0 | AK130: =SUM(AK93:AK129) -> 0 | AL130: =SUM(AL93:AL129) -> 124 | AN130: =SUM(AN93:AN129) -> 111.6 | AO130: =SUM(AO93:AO129) -> 95 | AQ130: =SUM(AQ93:AQ129) -> 1615 | AR130: =SUM(AR93:AR129) -> 0 | AT130: =SUM(AT93:AT129) -> 0 | AU130: =SUM(AU93:AU129) -> 25 | AW130: =SUM(AW93:AW129) -> 1875 | AX130: =SUM(AX93:AX129) -> 0 | AZ130: =SUM(AZ93:AZ129) -> 0 | BA130: =SUM(BA93:BA129) -> 0 | BC130: =SUM(BC93:BC129) -> 0 | BD130: =SUM(BD93:BD129) -> 1844 | BF130: =SUM(BF93:BF129) -> 19569.6 | BG130: =SUM(BG93:BG129) -> 4100 | BI130: =SUM(BI93:BI129) -> 25737.8 | BJ130: =SUM(BJ93:BJ129) -> 1055 | BL130: =SUM(BL93:BL129) -> 3903.5 | BM130: =SUM(BM93:BM129) -> 0 | BO130: =SUM(BO93:BO129) -> 0 | BP130: =SUM(BP93:BP129) -> 1881 | BR130: =SUM(BR93:BR129) -> 13795.2 | BS130: =SUM(BS93:BS129) -> 90 | BU130: =SUM(BU93:BU129) -> 687
...

Sheet 贾总购原材料
A1: 23年10月23日起贾总购货明细
A2: 日期 | B2: 客户名 | C2: 品名 | D2: 件数/桶 | E2: 规格/KG | F2: 数量/KG | G2: 单价/元 | H2: 金额/元 | I2: 备注
A3: 10-23日 | B3: 金银岛 | C3: 二甲苯 | D3: 6 | E3: 175 | F3: =E3*D3 -> 1050 | G3: 8.6 | H3: =F3*G3 -> 9030
A4: 10-23日 | B4: 金银岛 | C4: 环己酮 | D4: 6 | E4: 180 | F4: =E4*D4 -> 1080 | G4: 10.8 | H4: =F4*G4 -> 11664
A5: 10-23日 | B5: 金银岛 | C5: 仲丁酯 | D5: 5 | E5: 180 | F5: =E5*D5 -> 900 | G5: 7.2 | H5: =F5*G5 -> 6480 | I5: 溶剂购货单贾总于24/10日已提
A6: 10-23日 | B6: 金银岛 | C6: 粗甲酯 | D6: 4 | E6: 180 | F6: =E6*D6 -> 720 | G6: 4.2 | H6: =F6*G6 -> 3024
A7: 10-23日 | B7: 金银岛 | C7: 丁酯 | D7: 3 | E7: 180 | F7: =E7*D7 -> 540 | G7: 9.5 | H7: =F7*G7 -> 5130 | I7: =SUM(H3:H7) -> 35328
A8: 45223 | B8: 入库 | C8: 1160黑色浆 | D8: 3 | E8: 20 | F8: =E8*D8 -> 60 | I8: 无购货单：贾、李总经手
A9: 45223 | B9: 入库 | C9: 108树脂 | D9: 5 | E9: 190 | F9: =E9*D9 -> 950 | I9: 无购货单：贾、李总经手
A10: 45223 | B10: 入库 | C10: 730浆 | D10: 1 | E10: 1 | F10: 1120 | I10: 无购货单：贾、李总经手
A11: 45223 | B11: 入库 | C11: 715浆 | D11: 1 | E11: 1 | F11: 680 | I11: 无购货单：贾、李总经手
A12: 45228 | B12: 托运部送 | C12: 酞青蓝色粉 | D12: 2 | E12: 25 | F12: =E12*D12 -> 50 | I12: 无购货单：李总经手
A13: 45228 | B13: 托运部送 | C13: 托运费：李总付 | D13: 1 | E13: 1 | F13: 13 | I13: 无购货单：李总经手
A14: 45234 | B14: 送货未给单 | C14: 购30" | D14: 8 | E14: 25 | F14: =E14*D14 -> 200 | I14: 无购货单：李总经手
A15: 24购材料
A17: 45348 | B17: 赵永平 | C17: R369钛白粉 | D17: 80 | E17: 25 | F17: =E17*D17 -> 2000 | G17: 16.6 | H17: =F17*G17 -> 33200 | I17: =H17 -> 33200
A18: 45357 | B18: 715粉 | C18: 715粉 | D18: 2 | E18: 25 | F18: =E18*D18 -> 50 | G18: 28 | H18: =F18*G18 -> 1400
A19: 45357 | B19: 730粉 | C19: 730粉 | D19: 2 | E19: 25 | F19: =E19*D19 -> 50 | G19: 28 | H19: =F19*G19 -> 1400 | I19: =SUM(H18:H19) -> 2800
A20: 45357 | B20: 入库：贾总带来 | C20: 1206树脂 | D20: 1 | E20: 190 | F20: =E20*D20 -> 190
A21: 45369 | B21: 文萱：长圣 | C21: 5014分散剂 | D21: 1 | E21: 25 | F21: =E21*D21 -> 25 | G21: 56 | H21: =F21*G21 -> 1400
A22: 45369 | B22: 文萱：长圣 | C22: 5050分散剂 | D22: 1 | E22: 25 | F22: =E22*D22 -> 25 | G22: 56 | H22: =F22*G22 -> 1400
A23: 45369 | B23: 文萱：长圣 | C23: 7900-20X防尘浆 | D23: 3 | E23: 16 | F23: =E23*D23 -> 48 | G23: 38 | H23: =F23*G23 -> 1824 | I23: =SUM(H21:H23) -> 4624 | J23: 田如海：028-83989981
A24: 45371 | B24: 余氏东风 | C24: 酞青蓝粉 | D24: 2 | E24: 25 | F24: =E24*D24 -> 50 | H24: =F24*G24 -> 0 | I24: 无货单
A25: 45371 | B25: 余氏东风 | C25: 购中络黄粉 | D25: 4 | E25: 25 | F25: =E25*D25 -> 100 | H25: =F25*G25 -> 0 | I25: 无货单
A26: 45371 | B26: 余氏东风 | C26: 托运费：李总付:37 | D26: 6 | E26: 1 | F26: =E26*D26 -> 6 | G26: 6.17 | H26: 37
A27: 45357 | B27: 715粉 | C27: 715粉 | D27: 12 | E27: 25 | F27: =E27*D27 -> 300 | G27: 26 | H27: =F27*G27 -> 7800
A28: 45357 | B28: 730粉 | C28: 730粉 | D28: 8 | E28: 25 | F28: =E28*D28 -> 200 | G28: 26 | H28: =F28*G28 -> 5200 | I28: =SUM(H27:H28) -> 13000 | J28: 无货单：蓉经手
A29: 45378 | B29: 入库：贾总带来 | C29: 1206树脂 | D29: 1 | E29: 190 | F29: =E29*D29 -> 190
A30: 45411 | B30: 广汉 | C30: 五星花印方桶 | D30: 980 | E30: 1 | F30: =E30*D30 -> 980 | G30: 11.5 | H30: =F30*G30 -> 11270
A31: 日期 | C31: 品名 | D31: 数量/件 | E31: 规格/kg | F31: 数量/KG
A32: 45418 | C32: 购108树脂：夏 | D32: 6 | E32: 190 | F32: =D32*E32 -> 1140
A33: 45418 | C33: 购中络黄色粉 | D33: 8 | E33: 25 | F33: =D33*E33 -> 200 | G33: 有托运单、无货单
A34: 45418 | C34: 购5RK大红粉 | D34: 2 | E34: 25 | F34: =D34*E34 -> 50 | G34: 有托运单、无货单
A35: 45422 | C35: 购三木108树脂 | D35: 4 | E35: 190 | F35: =D35*E35 -> 760 | G35: 老板经手
A36: 45427 | C36: 购715粉 | D36: 12 | E36: 25 | F36: =D36*E36 -> 300 | G36: 25.5
A37: 45427 | C37: 购730粉 | D37: 8 | E37: 25 | F37: =D37*E37 -> 200 | G37: 25.5
A38: 45428 | C38: 购730粉 | D38: 8 | E38: 25 | F38: =D38*E38 -> 200 | H38: 无单
A39: 45429 | C39: 聚酮粉：CF-120 | D39: 20 | E39: 25 | F39: =D39*E39 -> 500
A40: 45449 | C40: 购715粉 | D40: 12 | E40: 25 | F40: =D40*E40 -> 300
A41: 45449 | C41: 购730粉 | D41: 8 | E41: 25 | F41: =D41*E41 -> 200
A42: 6月 | C42: 购108树脂：夏 | D42: 6 | E42: 190 | F42: =D42*E42 -> 1140
A43: 45467 | C43: 购5R大红粉
A44: 45470 | B44: 二千金鞋厂对公赵永平35200元购钛白粉
A46: 24.10.29 | C46: 购715浆新 | D46: 6 | E46: 200 | F46: =D46*E46 -> 1200
A47: 24.10.29 | C47: 购730浆新 | D47: 7 | E47: 185 | F47: =D47*E47 -> 1295
A48: 45705 | B48: 鑫业 | C48: F5RK:大红 | D48: 4 | E48: 25 | F48: 49 | G48: =SUM(D48*E48*F48) -> 4900
A49: 45705 | B49: 鑫业 | C49: 103-2A：中络黄 | D49: 8 | E49: 25 | F49: 26.5 | G49: =SUM(D49*E49*F49) -> 5300 | H49: =SUM(G48:G49) -> 10200
A50: 45709 | B50: 科立孚 | C50: 聚酮粉：CF-120 | D50: 40 | E50: 25 | F50: =D50*E50 -> 1000
